Workbook

Sheet Cover Page
C11: DCF Valuation Modeling
C13: Table of Contents | I13: Model Checks
C15: Outputs | I15: Incorrect Date Set for Valuation? | N15: =Inputs!$F$121 -> 0
C16: Inputs | I16: Incorrect Date Set for First Cash Flow? | N16: =Inputs!$F$122 -> 0
C17: Model | I17: Terminal Growth Rate Greater Than or Equal To WACC? | N17: =Inputs!F114 -> 0
I18: Unused Tax Losses Remaining? (Levered Schedule) | N18: =Model!D181 -> 0
I19: Unused Tax Losses Remaining? (Unlevered Schedule) | N19: =Model!D223 -> 0
I20: Two UFCF Methods Different? | N20: =IF(SUM(Model!I289:N289),1,0) -> 0

Sheet Outputs
B3: Dashboard: Perpetuity Method
D6: Model Drivers Set To | F6: 2 | L6: All figures in USD thousands unless stated
D9: Main Outputs 1 | L9: Selected Inputs
F11: Enterprise | G11: Equity | H11: Equity
F12: Value | G12: Value | H12: Per Share | L12: Terminal Growth Rate | O12: =Inputs!F111 -> 0.02
F13: =Model!H330 -> 115360.34 | L13: WACC | O13: =Inputs!L89 -> 0.058432496
D14: Best Case | E14: 1 | F14: 123125.17 | G14: =F14-O$14 -> 115112.17 | H14: =G14/O$15 -> 426.49934 | L14: Net Debt | N14: =CONCATENATE("(End of ",Model!$H$5,")") -> (End of 2025) | O14: =Inputs!L98 -> 8013
D15: Base Case | E15: 2 | F15: 115360.34 | G15: =F15-O$14 -> 107347.34 | H15: =G15/O$15 -> 397.73004 | L15: Shares Outstanding | N15: (FD 000) | O15: =Inputs!F109 -> 269.9
D16: Worst Case | E16: 3 | F16: 107048.61 | G16: =F16-O$14 -> 99035.606 | H16: =G16/O$15 -> 366.93444 | L16: Current Stock Price | N16: (US$/sh) | O16: =Inputs!F110 -> 357.05
D20: Enterprise Value 1 | L20: Equity Value per Share
D22: Terminal Growth Rate | L22: Terminal Growth Rate
C23: =Model!H330 -> 115360.34 | D23: =E23-0.005 -> 0.01 | E23: =F23-0.005 -> 0.015 | F23: =Inputs!F111 -> 0.02 | G23: =F23+0.005 -> 0.025 | H23: =G23+0.005 -> 0.03 | L23: =D23 -> 0.01 | M23: =E23 -> 0.015 | N23: =F23 -> 0.02 | O23: =G23 -> 0.025 | P23: =H23 -> 0.03
B24: WACC | C24: =C25-0.01 -> 0.038432496 | D24: 163083.72 | E24: 193701.35 | F24: 240929.65 | G24: 323317.69 | H24: 503408.76 | J24: WACC | K24: =C24 -> 0.038432496 | L24: =D37/$O$15 -> 574.5488 | M24: =E37/$O$15 -> 687.98942 | N24: =F37/$O$15 -> 862.97387 | O24: =G37/$O$15 -> 1168.2278 | P24: =H37/$O$15 -> 1835.4789
C25: =C26-0.01 -> 0.048432496 | D25: 120412.88 | E25: 135569 | F25: 156055.68 | G25: 185285.21 | H25: 230372.35 | K25: =C25 -> 0.048432496 | L25: =D38/$O$15 -> 416.45008 | M25: =E38/$O$15 -> 472.60465 | N25: =F38/$O$15 -> 548.50936 | O25: =G38/$O$15 -> 656.807 | P25: =H38/$O$15 -> 823.85829
C26: =Inputs!L89 -> 0.058432496 | D26: 95375.914 | E26: 104217.81 | F26: 115360.34 | G26: 129835.71 | H26: 149402.21 | K26: =C26 -> 0.058432496 | L26: =D39/$O$15 -> 323.68623 | M26: =E39/$O$15 -> 356.44613 | N26: =F39/$O$15 -> 397.73004 | O26: =G39/$O$15 -> 451.36238 | P26: =H39/$O$15 -> 523.85777
C27: =C26+0.01 -> 0.068432496 | D27: 78918.71 | E27: 84610.731 | F27: 91478 | G27: 99926.405 | H27: 110573.06 | K27: =C27 -> 0.068432496 | L27: =D40/$O$15 -> 262.71104 | M27: =E40/$O$15 -> 283.80041 | N27: =F40/$O$15 -> 309.24416 | O27: =G40/$O$15 -> 340.54615 | P27: =H40/$O$15 -> 379.9928
C28: =C27+0.01 -> 0.078432496 | D28: 67279.472 | E28: 71192.975 | F28: 75776.227 | G28: 81217.243 | H28: 87781.681 | K28: =C28 -> 0.078432496 | L28: =D41/$O$15 -> 219.58678 | M28: =E41/$O$15 -> 234.08661 | N28: =F41/$O$15 -> 251.0679 | O28: =G41/$O$15 -> 271.22728 | P28: =H41/$O$15 -> 295.54902
D33: Equity Value | L33: Premium (Discount) to Stock Price
D35: Terminal Growth Rate | L35: Terminal Growth Rate
D36: =D23 -> 0.01 | E36: =E23 -> 0.015 | F36: =F23 -> 0.02 | G36: =G23 -> 0.025 | H36: =H23 -> 0.03 | L36: =D36 -> 0.01 | M36: =E36 -> 0.015 | N36: =F36 -> 0.02 | O36: =G36 -> 0.025 | P36: =H36 -> 0.03
B37: WACC | C37: =C24 -> 0.038432496 | D37: =D24-$O$14 -> 155070.72 | E37: =E24-$O$14 -> 185688.35 | F37: =F24-$O$14 -> 232916.65 | G37: =G24-$O$14 -> 315304.69 | H37: =H24-$O$14 -> 495395.76 | J37: WACC | K37: =C37 -> 0.038432496 | L37: =L24/$O$16-1 -> 0.60915502 | M37: =M24/$O$16-1 -> 0.92687137 | N37: =N24/$O$16-1 -> 1.4169552 | O37: =O24/$O$16-1 -> 2.2718886 | P37: =P24/$O$16-1 -> 4.1406776
C38: =C25 -> 0.048432496 | D38: =D25-$O$14 -> 112399.88 | E38: =E25-$O$14 -> 127556 | F38: =F25-$O$14 -> 148042.68 | G38: =G25-$O$14 -> 177272.21 | H38: =H25-$O$14 -> 222359.35 | K38: =C38 -> 0.048432496 | L38: =L25/$O$16-1 -> 0.16636348 | M38: =M25/$O$16-1 -> 0.32363717 | N38: =N25/$O$16-1 -> 0.53622564 | O38: =O25/$O$16-1 -> 0.83953788 | P38: =P25/$O$16-1 -> 1.3074031
C39: =C26 -> 0.058432496 | D39: =D26-$O$14 -> 87362.914 | E39: =E26-$O$14 -> 96204.811 | F39: =F26-$O$14 -> 107347.34 | G39: =G26-$O$14 -> 121822.71 | H39: =H26-$O$14 -> 141389.21 | K39: =C39 -> 0.058432496 | L39: =L26/$O$16-1 -> -0.093442841 | M39: =M26/$O$16-1 -> -0.0016912733 | N39: =N26/$O$16-1 -> 0.11393373 | O39: =O26/$O$16-1 -> 0.26414335 | P39: =P26/$O$16-1 -> 0.46718323
C40: =C27 -> 0.068432496 | D40: =D27-$O$14 -> 70905.71 | E40: =E27-$O$14 -> 76597.731 | F40: =F27-$O$14 -> 83465 | G40: =G27-$O$14 -> 91913.405 | H40: =H27-$O$14 -> 102560.06 | K40: =C40 -> 0.068432496 | L40: =L27/$O$16-1 -> -0.26421778 | M40: =M27/$O$16-1 -> -0.20515219 | N40: =N27/$O$16-1 -> -0.13389115 | O40: =O27/$O$16-1 -> -0.046222803 | P40: =P27/$O$16-1 -> 0.064256542
C41: =C28 -> 0.078432496 | D41: =D28-$O$14 -> 59266.472 | E41: =E28-$O$14 -> 63179.975 | F41: =F28-$O$14 -> 67763.227 | G41: =G28-$O$14 -> 73204.243 | H41: =H28-$O$14 -> 79768.681 | K41: =C41 -> 0.078432496 | L41: =L28/$O$16-1 -> -0.38499712 | M41: =M28/$O$16-1 -> -0.34438704 | N41: =N28/$O$16-1 -> -0.29682705 | O41: =O28/$O$16-1 -> -0.24036611 | P41: =P28/$O$16-1 -> -0.17224752
H42: \
P43: These tables require the workbook calculation to be set to automatic to update.
B47: Dashboard: Multiple Method
D50: Model Drivers Set To | L50: All figures in USD thousands unless stated
D53: Main Outputs 1 | L53: Selected Inputs
F55: Enterprise | G55: Equity | H55: Equity
F56: Value | G56: Value | H56: Per Share | L56: Terminal Multiple | O56: =Inputs!F112 -> 16
F57: =Model!H377 -> 116409.17 | L57: WACC | O57: =Inputs!L89 -> 0.058432496
D58: =D14 -> Best Case | E58: 1 | F58: 125072.87 | G58: =F58-O$58 -> 117059.87 | H58: =G58/O$59 -> 433.71571 | L58: Net Debt | N58: =N14 -> (End of 2025) | O58: =Inputs!L98 -> 8013
D59: =D15 -> Base Case | E59: 2 | F59: 116409.17 | G59: =F59-O$58 -> 108396.17 | H59: =G59/O$59 -> 401.61604 | L59: Shares Outstanding | N59: (FD 000) | O59: =Inputs!F109 -> 269.9
D60: =D16 -> Worst Case | E60: 3 | F60: 108254.17 | G60: =F60-O$58 -> 100241.17 | H60: =G60/O$59 -> 371.40113 | L60: Current Stock Price | N60: (US$/sh) | O60: =Inputs!F110 -> 357.05
D64: Enterprise Value 1 | L64: Equity Value per Share
D66: Terminal Multiple | L66: Terminal Multiple
C67: =Model!H377 -> 116409.17 | D67: =E67-0.5 -> 15 | E67: =F67-0.5 -> 15.5 | F67: =Inputs!F112 -> 16 | G67: =+F67+0.5 -> 16.5 | H67: =+G67+0.5 -> 17 | L67: =D67 -> 15 | M67: =E67 -> 15.5 | N67: =F67 -> 16 | O67: =G67 -> 16.5 | P67: =H67 -> 17
B68: WACC | C68: =C69-0.01 -> 0.038432496 | D68: 122375.09 | E68: 125670.16 | F68: 128965.23 | G68: 132260.3 | H68: 135555.37 | J68: WACC | K68: =C68 -> 0.038432496 | L68: =D81/$O$59 -> 423.72024 | M68: =E81/$O$59 -> 435.92872 | N68: =F81/$O$59 -> 448.13721 | O68: =G81/$O$59 -> 460.34569 | P68: =H81/$O$59 -> 472.55417
C69: =C70-0.01 -> 0.048432496 | D69: 116256.75 | E69: 119372.43 | F69: 122488.11 | G69: 125603.78 | H69: 128719.46 | K69: =C69 -> 0.048432496 | L69: =D82/$O$59 -> 401.05131 | M69: =E82/$O$59 -> 412.59513 | N69: =F82/$O$59 -> 424.13896 | O69: =G82/$O$59 -> 435.68279 | P69: =H82/$O$59 -> 447.22661
C70: =Inputs!L89 -> 0.058432496 | D70: 110513.93 | E70: 113461.55 | F70: 116409.17 | G70: 119356.79 | H70: 122304.41 | K70: =C70 -> 0.058432496 | L70: =D83/$O$59 -> 379.77372 | M70: =E83/$O$59 -> 390.69488 | N70: =F83/$O$59 -> 401.61604 | O70: =G83/$O$59 -> 412.5372 | P70: =H83/$O$59 -> 423.45836
C71: =C70+0.01 -> 0.068432496 | D71: 105120.08 | E71: 107910.16 | F71: 110700.24 | G71: 113490.33 | H71: 116280.41 | K71: =C71 -> 0.068432496 | L71: =D84/$O$59 -> 359.7891 | M71: =E84/$O$59 -> 370.12657 | N71: =F84/$O$59 -> 380.46404 | O71: =G84/$O$59 -> 390.80151 | P71: =H84/$O$59 -> 401.13898
C72: =C71+0.01 -> 0.078432496 | D72: 100050.77 | E72: 102693.08 | F72: 105335.4 | G72: 107977.71 | H72: 110620.03 | K72: =C72 -> 0.078432496 | L72: =D85/$O$59 -> 341.00692 | M72: =E85/$O$59 -> 350.7969 | N72: =F85/$O$59 -> 360.58688 | O72: =G85/$O$59 -> 370.37686 | P72: =H85/$O$59 -> 380.16684
D77: Equity Value | L77: Premium (Discount) to Stock Price
D79: Terminal Multiple | L79: Terminal Multiple
D80: =D67 -> 15 | E80: =E67 -> 15.5 | F80: =F67 -> 16 | G80: =G67 -> 16.5 | H80: =H67 -> 17 | L80: =D80 -> 15 | M80: =E80 -> 15.5 | N80: =F80 -> 16 | O80: =G80 -> 16.5 | P80: =H80 -> 17
B81: WACC | C81: =C68 -> 0.038432496 | D81: =D68-$O$58 -> 114362.09 | E81: =E68-$O$58 -> 117657.16 | F81: =F68-$O$58 -> 120952.23 | G81: =G68-$O$58 -> 124247.3 | H81: =H68-$O$58 -> 127542.37 | J81: WACC | K81: =C81 -> 0.038432496 | L81: =L68/$O$60-1 -> 0.18672523 | M81: =M68/$O$60-1 -> 0.22091787 | N81: =N68/$O$60-1 -> 0.2551105 | O81: =O68/$O$60-1 -> 0.28930314 | P81: =P68/$O$60-1 -> 0.32349578
C82: =C69 -> 0.048432496 | D82: =D69-$O$58 -> 108243.75 | E82: =E69-$O$58 -> 111359.43 | F82: =F69-$O$58 -> 114475.11 | G82: =G69-$O$58 -> 117590.78 | H82: =H69-$O$58 -> 120706.46 | K82: =C82 -> 0.048432496 | L82: =L69/$O$60-1 -> 0.1232357 | M82: =M69/$O$60-1 -> 0.15556682 | N82: =N69/$O$60-1 -> 0.18789794 | O82: =O69/$O$60-1 -> 0.22022906 | P82: =P69/$O$60-1 -> 0.25256019
C83: =C70 -> 0.058432496 | D83: =D70-$O$58 -> 102500.93 | E83: =E70-$O$58 -> 105448.55 | F83: =F70-$O$58 -> 108396.17 | G83: =G70-$O$58 -> 111343.79 | H83: =H70-$O$58 -> 114291.41 | K83: =C83 -> 0.058432496 | L83: =L70/$O$60-1 -> 0.063642952 | M83: =M70/$O$60-1 -> 0.094230153 | N83: =N70/$O$60-1 -> 0.12481735 | O83: =O70/$O$60-1 -> 0.15540455 | P83: =P70/$O$60-1 -> 0.18599176
C84: =C71 -> 0.068432496 | D84: =D71-$O$58 -> 97107.079 | E84: =E71-$O$58 -> 99897.162 | F84: =F71-$O$58 -> 102687.24 | G84: =G71-$O$58 -> 105477.33 | H84: =H71-$O$58 -> 108267.41 | K84: =C84 -> 0.068432496 | L84: =L71/$O$60-1 -> 0.0076714858 | M84: =M71/$O$60-1 -> 0.036623924 | N84: =N71/$O$60-1 -> 0.065576363 | O84: =O71/$O$60-1 -> 0.094528801 | P84: =P71/$O$60-1 -> 0.12348124
C85: =C72 -> 0.078432496 | D85: =D72-$O$58 -> 92037.767 | E85: =E72-$O$58 -> 94680.082 | F85: =F72-$O$58 -> 97322.398 | G85: =G72-$O$58 -> 99964.714 | H85: =H72-$O$58 -> 102607.03 | K85: =C85 -> 0.078432496 | L85: =L72/$O$60-1 -> -0.044932317 | M85: =M72/$O$60-1 -> -0.017513242 | N85: =N72/$O$60-1 -> 0.009905832 | O85: =O72/$O$60-1 -> 0.037324906 | P85: =P72/$O$60-1 -> 0.064743981
P87: These tables require the workbook calculation to be set to automatic to update.

Sheet Inputs
B3: Drivers
B5: All figures in USD thousands | G5: =F101 -> 2026 | H5: =G5+1 -> 2027 | I5: =H5+1 -> 2028 | J5: =I5+1 -> 2029 | K5: =J5+1 -> 2030 | L5: Term
B7: Driver Switch | D7: =Outputs!F6 -> 2
B10: Aerospace revenue growth | G10: {=INDEX(G12:G14,$D$7)} -> 0.037 | H10: {=INDEX(H12:H14,$D$7)} -> 0.04 | I10: {=INDEX(I12:I14,$D$7)} -> 0.04 | J10: {=INDEX(J12:J14,$D$7)} -> 0.04 | K10: {=INDEX(K12:K14,$D$7)} -> 0.04 | L10: {=INDEX(L12:L14,$D$7)} -> 0.04
B12: Best Case | G12: 0.05 | H12: 0.05 | I12: 0.05 | J12: 0.05 | K12: 0.05 | L12: 0.05
B13: Base Case | G13: 0.037 | H13: 0.04 | I13: 0.04 | J13: 0.04 | K13: 0.04 | L13: 0.04
B14: Worst Case | G14: 0.03 | H14: 0.03 | I14: 0.03 | J14: 0.03 | K14: 0.03 | L14: 0.03
B16: Marine Systems revenue growth | G16: {=INDEX(G18:G20,$D$7)} -> 0.046 | H16: {=INDEX(H18:H20,$D$7)} -> 0.05 | I16: {=INDEX(I18:I20,$D$7)} -> 0.05 | J16: {=INDEX(J18:J20,$D$7)} -> 0.05 | K16: {=INDEX(K18:K20,$D$7)} -> 0.05 | L16: {=INDEX(L18:L20,$D$7)} -> 0.05
B18: Best Case | G18: 0.06 | H18: 0.06 | I18: 0.06 | J18: 0.06 | K18: 0.06 | L18: 0.06
B19: Base Case | G19: 0.046 | H19: 0.05 | I19: 0.05 | J19: 0.05 | K19: 0.05 | L19: 0.05
B20: Worst Case | G20: 0.04 | H20: 0.04 | I20: 0.04 | J20: 0.04 | K20: 0.04 | L20: 0.04
B22: Combat Systems revenue growth | G22: {=INDEX(G24:G26,$D$7)} -> 0.049 | H22: {=INDEX(H24:H26,$D$7)} -> 0.05 | I22: {=INDEX(I24:I26,$D$7)} -> 0.05 | J22: {=INDEX(J24:J26,$D$7)} -> 0.05 | K22: {=INDEX(K24:K26,$D$7)} -> 0.05 | L22: {=INDEX(L24:L26,$D$7)} -> 0.05
B24: Best Case | G24: 0.06 | H24: 0.06 | I24: 0.06 | J24: 0.06 | K24: 0.06 | L24: 0.06
B25: Base Case | G25: 0.049 | H25: 0.05 | I25: 0.05 | J25: 0.05 | K25: 0.05 | L25: 0.05
B26: Worst Case | G26: 0.04 | H26: 0.04 | I26: 0.04 | J26: 0.04 | K26: 0.04 | L26: 0.04
B28: Technology revenue growth | G28: {=INDEX(G30:G32,$D$7)} -> 0.024 | H28: {=INDEX(H30:H32,$D$7)} -> 0.02 | I28: {=INDEX(I30:I32,$D$7)} -> 0.02 | J28: {=INDEX(J30:J32,$D$7)} -> 0.02 | K28: {=INDEX(K30:K32,$D$7)} -> 0.02 | L28: {=INDEX(L30:L32,$D$7)} -> 0.02
B30: Best Case | G30: 0.03 | H30: 0.03 | I30: 0.03 | J30: 0.03 | K30: 0.03 | L30: 0.03
B31: Base Case | G31: 0.024 | H31: 0.02 | I31: 0.02 | J31: 0.02 | K31: 0.02 | L31: 0.02
B32: Worst Case | G32: 0.01 | H32: 0.01 | I32: 0.01 | J32: 0.01 | K32: 0.01 | L32: 0.01
B35: Capital Expenditure | G35: {=INDEX(G37:G39,$D$7)} -> 1091.6137 | H35: {=INDEX(H37:H39,$D$7)} -> 1135.1988 | I35: {=INDEX(I37:I39,$D$7)} -> 1180.6889 | J35: {=INDEX(J37:J39,$D$7)} -> 1228.1715 | K35: {=INDEX(K37:K39,$D$7)} -> 1277.7383 | L35: {=INDEX(L37:L39,$D$7)} -> 1329.4856
B37: Best Case | G37: =Model!I37*0.018 -> 982.45235 | H37: =Model!J37*0.018 -> 1021.6789 | I37: =Model!K37*0.018 -> 1062.62 | J37: =Model!L37*0.018 -> 1105.3543 | K37: =Model!M37*0.018 -> 1149.9645 | L37: =Model!N37*0.018 -> 1196.537
B38: Base Case | G38: =Model!I37*0.02 -> 1091.6137 | H38: =Model!J37*0.02 -> 1135.1988 | I38: =Model!K37*0.02 -> 1180.6889 | J38: =Model!L37*0.02 -> 1228.1715 | K38: =Model!M37*0.02 -> 1277.7383 | L38: =Model!N37*0.02 -> 1329.4856
B39: Worst Case | G39: =Model!I37*0.023 -> 1255.3558 | H39: =Model!J37*0.023 -> 1305.4786 | I39: =Model!K37*0.023 -> 1357.7922 | J39: =Model!L37*0.023 -> 1412.3972 | K39: =Model!M37*0.023 -> 1469.3991 | L39: =Model!N37*0.023 -> 1528.9084
B42: Inflation Rate | G42: 0.032 | H42: 0.024 | I42: 0.03 | J42: 0.03 | K42: 0.03 | L42: 0.03
B44: Working Capital
B45: Accounts Receivable | G45: 72 | H45: 70 | I45: 70 | J45: 70 | K45: 70 | L45: 70
B46: Inventory | G46: 75 | H46: 72 | I46: 72 | J46: 72 | K46: 72 | L46: 72
B47: Accounts Payable | G47: 22 | H47: 20 | I47: 20 | J47: 20 | K47: 20 | L47: 20
B50: WACC
B52: All figures in USD thousands unless stated
H54: Average | I54: Debt/ | J54: Debt/ | K54: Levered | L54: Unlevered
B55: Name | D55: Region | F55: Debt | G55: Equity | H55: Tax Rate 1 | I55: Equity | J55: Capital | K55: Beta 2 | L55: Beta 3
B57: Lockheed Martin | D57: USA | F57: 19874 | G57: 106200 | H57: 0.165 | I57: =F57/G57 -> 0.18713748 | J57: =F57/(F57+G57) -> 0.15763758 | K57: 0.49 | L57: =K57/(1+(1-H57)*I57) -> 0.42378019
B58: Northrop Grumman | D58: USA | F58: 15204 | G58: 68100 | H58: 0.172 | I58: =F58/G58 -> 0.22325991 | J58: =F58/(F58+G58) -> 0.18251224 | K58: 0.45 | L58: =K58/(1+(1-H58)*I58) -> 0.37979196
B59: Raytheon Technologies | D59: USA | F59: 31392 | G59: 132500 | H59: 0.184 | I59: =F59/G59 -> 0.23692075 | J59: =F59/(F59+G59) -> 0.19154077 | K59: 0.79 | L59: =K59/(1+(1-H59)*I59) -> 0.6620145
B60: L3Harris Technologies | D60: USA | F60: 8141 | G60: 34800 | H60: 0.168 | I60: =F60/G60 -> 0.23393678 | J60: =F60/(F60+G60) -> 0.18958571 | K60: 0.55 | L60: =K60/(1+(1-H60)*I60) -> 0.46039151
B61: Huntington Ingalls | D61: USA | F61: 2474 | G61: 11200 | H61: 0.179 | I61: =F61/G61 -> 0.22089286 | J61: =F61/(F61+G61) -> 0.18092731 | K61: 0.63 | L61: =K61/(1+(1-H61)*I61) -> 0.53328682
G63: Average | H63: =AVERAGE(H57:H61) -> 0.1736 | I63: =AVERAGE(I57:I61) -> 0.22042956 | J63: =AVERAGE(J57:J61) -> 0.18044072 | K63: =AVERAGE(K57:K61) -> 0.582 | L63: =AVERAGE(L57:L61) -> 0.491853
G64: Median | H64: =MEDIAN(H57:H61) -> 0.172 | I64: =MEDIAN(I57:I61) -> 0.22325991 | J64: =MEDIAN(J57:J61) -> 0.18251224 | K64: =MEDIAN(K57:K61) -> 0.55 | L64: =MEDIAN(L57:L61) -> 0.46039151
B67: Risk Premium for Equity | H67: Cost of Equity
B69: Market Risk Premium | F69: 0.0433 | H69: Risk Free Rate | L69: 0.0415
B70: Average Unlevered Beta | F70: =L63 -> 0.491853 | H70: Equity Risk Premium | L70: =F72 -> 0.026792128
B71: Levered Beta 4 | F71: =F70*(1+(1-L78)*F82) -> 0.61875585 | H71: Country Risk Premium | L71: 0.0007
B72: Equity Risk Premium | F72: =F71*F69 -> 0.026792128 | H72: Cost of Equity | L72: =SUM(L69:L71) -> 0.068992128
B75: Capital Structure | H75: Cost of Debt
E77: Current | F77: Target | H77: Pre-Tax Cost of Debt | L77: 0.0299
B78: Total Debt | D78: 8013 | E78: =D78/D80 -> 0.23823398 | F78: =E78 -> 0.23823398 | H78: Tax Rate | L78: 0.175
B79: Market Capitalization | D79: 25622 | E79: =D79/D80 -> 0.76176602 | F79: =F80-F78 -> 0.76176602 | H79: After-Tax Cost of Debt | L79: =L77*(1-L78) -> 0.0246675
B80: Total Capitalization | D80: =SUM(D78:D79) -> 33635 | E80: =SUM(E78:E79) -> 1 | F80: =E80 -> 1
B82: Debt / Equity | E82: =E78/E79 -> 0.31273905 | F82: =F78/F79 -> 0.31273905 | H82: Weighted Average Cost of Capital
K84: Weight | L84: Cost
B85: Tax Rate is a 5-Year Average. | H85: Debt Capital | K85: =F78 -> 0.23823398 | L85: =L79 -> 0.0246675
B86: Levered beta is based on 5-year monthly data. | H86: Equity Capital | K86: =F79 -> 0.76176602 | L86: =L72 -> 0.068992128
B87: Unlevered Beta = Levered Beta / (1 + (1 - Tax Rate) × Debt-to-Equity)
B88: Levered Beta = Unlevered Beta x (1 + (1 - Tax rate) x (Debt-to-Equity))
H89: Weighted Average Cost of Capital | L89: =K85*L85+K86*L86 -> 0.058432496
B92: Other Inputs
B94: All figures in USD thousands unless stated
B97: Dates | H97: =CONCATENATE("End of ",G5-1," Balances") -> End of 2025 Balances
B98: Valuation Date | E98: (YY-MM-DD) | F98: 46081 | H98: Net Debt | L98: =7007+1006 -> 8013
B99: First Expected Cash Flow | E99: (YY-MM-DD) | F99: 46387 | H99: Property Plant & Equipment | L99: 7525
B100: First Fiscal Year End for Forecast | E100: (YY-MM-DD) | F100: 46387 | H100: Tax Basis for PP&E | L100: 5382
B101: First Year of Forecast | E101: (YYYY) | F101: 2026 | H101: Tax Losses | L101: 663
B102: Incorrect Date Set for Valuation? | F102: =IF(F98>F99,1,0) -> 0
B103: Incorrect Date Set for First Cash Flow? | F103: =IF(F99>F100,1,0) -> 0
B104: Days in Period | F104: 365
B108: Valuation | H108: Other Inputs
B109: Shares Outstanding | E109: (FD 000) | F109: 269.9 | H109: Projected Interest Expense | L109: -250
B110: Current Stock Price | E110: (US$/sh) | F110: 357.05 | H110: First Year Tax Depreciation | L110: 0.5
B111: Terminal Growth Rate | F111: 0.02 | H111: Blended Tax Depreciation Rate | L111: 0.175
B112: Terminal EBITDA Multiple 1 | F112: 16 | H112: First Year Accounting Depreciation | L112: 0.5
B113: Weighted Average Cost of Capital (WACC) | F113: =L89 -> 0.058432496 | H113: Useful Life: Existing Assets | K113: (Years) | L113: 12
B114: Terminal Growth Greater Than or Equal To WACC? | F114: =IF(F111>F113,1,0) -> 0 | H114: Useful Life: New Assets | K114: (Years) | L114: 30

Sheet Model
B3: Revenue Schedule
F5: 2023 | G5: =F5+1 -> 2024 | H5: =G5+1 -> 2025 | I5: =H5+1 -> 2026 | J5: =I5+1 -> 2027 | K5: =J5+1 -> 2028 | L5: =K5+1 -> 2029 | M5: =L5+1 -> 2030 | N5: Term
B7: Revenue Growth Aerospace | G7: =G9/F9-1 -> 0.30483703 | H7: =H9/G9-1 -> 0.16543693 | I7: =Inputs!G10 -> 0.037 | J7: =Inputs!H10 -> 0.04 | K7: =Inputs!I10 -> 0.04 | L7: =Inputs!J10 -> 0.04 | M7: =Inputs!K10 -> 0.04 | N7: =Inputs!L10 -> 0.04
B9: Aerospace revenue | F9: 8621 | G9: 11249 | H9: 13110 | I9: =H9*(1+I7) -> 13595.07 | J9: =I9*(1+J7) -> 14138.873 | K9: =J9*(1+K7) -> 14704.428 | L9: =K9*(1+L7) -> 15292.605 | M9: =L9*(1+M7) -> 15904.309 | N9: =M9*(1+N7) -> 16540.481
B11: Revenue Growth Marine Systems | G11: =G13/F13-1 -> 0.15103122 | H11: =H13/G13-1 -> 0.1659346 | I11: =Inputs!G16 -> 0.046 | J11: =Inputs!H16 -> 0.05 | K11: =Inputs!I16 -> 0.05 | L11: =Inputs!J16 -> 0.05 | M11: =Inputs!K16 -> 0.05 | N11: =Inputs!L16 -> 0.05
B13: Marine Systems revenue | F13: 12461 | G13: 14343 | H13: 16723 | I13: =H13*(1+I11) -> 17492.258 | J13: =I13*(1+J11) -> 18366.871 | K13: =J13*(1+K11) -> 19285.214 | L13: =K13*(1+L11) -> 20249.475 | M13: =L13*(1+M11) -> 21261.949 | N13: =M13*(1+N11) -> 22325.046
B15: Revenue Growth Combat Systems | G15: =G17/F17-1 -> 0.088171263 | H15: =H17/G17-1 -> 0.027675892 | I15: =Inputs!G22 -> 0.049 | J15: =Inputs!H22 -> 0.05 | K15: =Inputs!I22 -> 0.05 | L15: =Inputs!J22 -> 0.05 | M15: =Inputs!K22 -> 0.05 | N15: =Inputs!L22 -> 0.05
B17: Combat Systems revenue | F17: 8268 | G17: 8997 | H17: 9246 | I17: =H17*(1+I15) -> 9699.054 | J17: =I17*(1+J15) -> 10184.007 | K17: =J17*(1+K15) -> 10693.207 | L17: =K17*(1+L15) -> 11227.867 | M17: =L17*(1+M15) -> 11789.261 | N17: =M17*(1+N15) -> 12378.724
B19: Revenue Growth Technologies | G19: =G21/F21-1 -> 0.015864417 | H19: =H21/G21-1 -> 0.026205531 | I19: =Inputs!G28 -> 0.024 | J19: =Inputs!H28 -> 0.02 | K19: =Inputs!I28 -> 0.02 | L19: =Inputs!J28 -> 0.02 | M19: =Inputs!K28 -> 0.02 | N19: =Inputs!L28 -> 0.02
B21: Technologies Revenue | F21: 12922 | G21: 13127 | H21: 13471 | I21: =H21*(1+I19) -> 13794.304 | J21: =I21*(1+J19) -> 14070.19 | K21: =J21*(1+K19) -> 14351.594 | L21: =K21*(1+L19) -> 14638.626 | M21: =L21*(1+M19) -> 14931.398 | N21: =M21*(1+N19) -> 15230.026
B24: Total Revenue | F24: =F9+F13+F17+F21 -> 42272 | G24: =G9+G13+G17+G21 -> 47716 | H24: =H9+H13+H17+H21 -> 52550 | I24: =I9+I13+I17+I21 -> 54580.686 | J24: =J9+J13+J17+J21 -> 56759.94 | K24: =K9+K13+K17+K21 -> 59034.443 | L24: =L9+L13+L17+L21 -> 61408.573 | M24: =M9+M13+M17+M21 -> 63886.917 | N24: =N9+N13+N17+N21 -> 66474.278
B27: Income Statement
B29: All figures in USD thousands unless stated | F29: 2023 | G29: =F29+1 -> 2024 | H29: =G29+1 -> 2025 | I29: =H29+1 -> 2026 | J29: =I29+1 -> 2027 | K29: =J29+1 -> 2028 | L29: =K29+1 -> 2029 | M29: =L29+1 -> 2030 | N29: Term
B32: Inflation | F32: 0.041 | G32: 0.029 | H32: 0.027 | I32: =Inputs!G42 -> 0.032 | J32: =Inputs!H42 -> 0.024 | K32: =Inputs!I42 -> 0.03 | L32: =Inputs!J42 -> 0.03 | M32: =Inputs!K42 -> 0.03 | N32: =Inputs!L42 -> 0.03
B34: Interest Expense | C34: =Inputs!L109 -> -250
B35: Tax Rate | C35: =Inputs!L78 -> 0.175
B37: Revenue | F37: =F24 -> 42272 | G37: =G24 -> 47716 | H37: =H24 -> 52550 | I37: =I24 -> 54580.686 | J37: =J24 -> 56759.94 | K37: =K24 -> 59034.443 | L37: =L24 -> 61408.573 | M37: =M24 -> 63886.917 | N37: =N24 -> 66474.278
B38: COGS | F38: =-20591-15009-F48-F47 -> -34737 | G38: =-24332-16020-G48-G47 -> -39466 | H38: =-27965-16634-H48-H47 -> -43675 | I38: =I37*-0.83 -> -45301.969 | J38: =J37*-0.83 -> -47110.751 | K38: =K37*-0.83 -> -48998.588 | L38: =L37*-0.83 -> -50969.116 | M38: =M37*-0.83 -> -53026.141 | N38: =N37*-0.83 -> -55173.651
B39: Gross Profit | F39: =SUM(F37:F38) -> 7535 | G39: =SUM(G37:G38) -> 8250 | H39: =SUM(H37:H38) -> 8875 | I39: =SUM(I37:I38) -> 9278.7166 | J39: =SUM(J37:J38) -> 9649.1899 | K39: =SUM(K37:K38) -> 10035.855 | L39: =SUM(L37:L38) -> 10439.457 | M39: =SUM(M37:M38) -> 10860.776 | N39: =SUM(N37:N38) -> 11300.627
B42: SG&A | F42: -2427 | G42: -2568 | H42: -2595 | I42: =H42*(1+I32) -> -2678.04 | J42: =I42*(1+J32) -> -2742.313 | K42: =J42*(1+K32) -> -2824.5823 | L42: =K42*(1+L32) -> -2909.3198 | M42: =L42*(1+M32) -> -2996.5994 | N42: =M42*(1+N32) -> -3086.4974
B43: Other | F43: 0 | G43: 0 | H43: 0 | I43: 0 | J43: 0 | K43: 0 | L43: 0 | M43: 0 | N43: 0
B44: EBITDA | F44: =SUM(F39:F43) -> 5108 | G44: =SUM(G39:G43) -> 5682 | H44: =SUM(H39:H43) -> 6280 | I44: =SUM(I39:I43) -> 6600.6766 | J44: =SUM(J39:J43) -> 6906.8769 | K44: =SUM(K39:K43) -> 7211.273 | L44: =SUM(L39:L43) -> 7530.1376 | M44: =SUM(M39:M43) -> 7864.1765 | N44: =SUM(N39:N43) -> 8214.1298
B47: Amortization | F47: -255 | G47: -242 | H47: -244 | I47: -175 | J47: -169 | K47: -147 | L47: -131 | M47: -121 | N47: -110
B48: Depreciation | F48: -608 | G48: -644 | H48: -680 | I48: =-I135 -> -645.2769 | J48: =-J135 -> -682.39044 | K48: =-K135 -> -720.98857 | L48: =-L135 -> -761.13624 | M48: =-M135 -> -802.9014 | N48: =-Inputs!L35 -> -1329.4856
B49: EBIT | F49: =F44+F48+F47 -> 4245 | G49: =G44+G48+G47 -> 4796 | H49: =H44+H48+H47 -> 5356 | I49: =I44+I48+I47 -> 5780.3997 | J49: =J44+J48+J47 -> 6055.4865 | K49: =K44+K48+K47 -> 6343.2844 | L49: =L44+L48+L47 -> 6638.0014 | M49: =M44+M48+M47 -> 6940.2751 | N49: =N44+N48+N47 -> 6774.6443
B51: Interest | F51: =-343+82 -> -261 | G51: =68-324 -> -256 | H51: =61-314 -> -253 | I51: =C34 -> -250 | J51: =I51 -> -250 | K51: =J51 -> -250 | L51: =K51 -> -250 | M51: =L51 -> -250 | N51: =M51 -> -250
B52: EBT | F52: =F49+F51 -> 3984 | G52: =G49+G51 -> 4540 | H52: =H49+H51 -> 5103 | I52: =I49+I51 -> 5530.3997 | J52: =J49+J51 -> 5805.4865 | K52: =K49+K51 -> 6093.2844 | L52: =L49+L51 -> 6388.0014 | M52: =M49+M51 -> 6690.2751 | N52: =N49+N51 -> 6524.6443
B54: Current Tax | F54: 846 | G54: 844 | H54: 637 | I54: =I204 -> 783.17932 | J54: =J204 -> 951.51065 | K54: =K204 -> 1005.3448 | L54: =L204 -> 1059.8122 | M54: =M204 -> 1115.1225 | N54: =N52*C35 -> 1141.8127
B55: Deferred Tax | F55: -177 | G55: -86 | H55: 256 | I55: =I205 -> 184.64063 | J55: =J205 -> 64.449485 | K55: =K205 -> 60.979976 | L55: =L205 -> 58.088036 | M55: =M205 -> 55.675673 | N55: =N205 -> 0
B56: Total Tax | F56: =SUM(F54:F55) -> 669 | G56: =SUM(G54:G55) -> 758 | H56: =SUM(H54:H55) -> 893 | I56: =SUM(I54:I55) -> 967.81995 | J56: =SUM(J54:J55) -> 1015.9601 | K56: =SUM(K54:K55) -> 1066.3248 | L56: =SUM(L54:L55) -> 1117.9002 | M56: =SUM(M54:M55) -> 1170.7981 | N56: =SUM(N54:N55) -> 1141.8127
B58: Net Income | F58: =F52-F56 -> 3315 | G58: =G52-G56 -> 3782 | H58: =H52-H56 -> 4210 | I58: =I52-I56 -> 4562.5798 | J58: =J52-J56 -> 4789.5263 | K58: =K52-K56 -> 5026.9596 | L58: =L52-L56 -> 5270.1011 | M58: =M52-M56 -> 5519.4769 | N58: =N52-N56 -> 5382.8315
B62: Working Capital Schedule
B64: All figures in USD thousands unless stated | F64: =F29 -> 2023 | G64: =G29 -> 2024 | H64: =H29 -> 2025 | I64: =I29 -> 2026 | J64: =J29 -> 2027 | K64: =K29 -> 2028 | L64: =L29 -> 2029 | M64: =M29 -> 2030 | N64: =N29 -> Term
B67: Days in Period | F67: 365 | G67: 365 | H67: 365 | I67: 365 | J67: 365 | K67: 365 | L67: 365 | M67: 365 | N67: 365
B68: Revenue | F68: =F37 -> 42272 | G68: =G37 -> 47716 | H68: =H37 -> 52550 | I68: =I37 -> 54580.686 | J68: =J37 -> 56759.94 | K68: =K37 -> 59034.443 | L68: =L37 -> 61408.573 | M68: =M37 -> 63886.917 | N68: =N37 -> 66474.278
B69: COGS | F69: =-F38 -> 34737 | G69: =-G38 -> 39466 | H69: =-H38 -> 43675 | I69: =-I38 -> 45301.969 | J69: =-J38 -> 47110.751 | K69: =-K38 -> 48998.588 | L69: =-L38 -> 50969.116 | M69: =-M38 -> 53026.141 | N69: =-N38 -> 55173.651
B72: AMOUNTS PER DAY 1
B73: Accounts Receivable | D73: (Days) | F73: =(F79/F68)*F$67 -> 94.988763 | G73: =(G79/G68)*G$67 -> 85.864804 | H73: =(H79/H68)*H$67 -> 74.917031 | I73: =Inputs!G45 -> 72 | J73: =Inputs!H45 -> 70 | K73: =Inputs!I45 -> 70 | L73: =Inputs!J45 -> 70 | M73: =Inputs!K45 -> 70 | N73: =Inputs!L45 -> 70
B74: Inventory | D74: (Days) | F74: =(F80/F69)*F$67 -> 90.133575 | G74: =(G80/G69)*G$67 -> 89.932093 | H74: =(H80/H69)*H$67 -> 77.15352 | I74: =Inputs!G46 -> 75 | J74: =Inputs!H46 -> 72 | K74: =Inputs!I46 -> 72 | L74: =Inputs!J46 -> 72 | M74: =Inputs!K46 -> 72 | N74: =Inputs!L46 -> 72
B75: Accounts Payable | D75: (Days) | F75: =(F81/F69)*F$67 -> 32.520799 | G75: =(G81/G69)*G$67 -> 30.926874 | H75: =(H81/H69)*H$67 -> 22.380538 | I75: =Inputs!G47 -> 22 | J75: =Inputs!H47 -> 20 | K75: =Inputs!I47 -> 20 | L75: =Inputs!J47 -> 20 | M75: =Inputs!K47 -> 20 | N75: =Inputs!L47 -> 20
B78: TOTAL AMOUNTS
B79: Accounts Receivable | F79: =3004+7997 -> 11001 | G79: =2977+8248 -> 11225 | H79: =2406+8380 -> 10786 | I79: =(I73/I$67)*I68 -> 10766.601 | J79: =(J73/J$67)*J68 -> 10885.468 | K79: =(K73/K$67)*K68 -> 11321.674 | L79: =(L73/L$67)*L68 -> 11776.987 | M79: =(M73/M$67)*M68 -> 12252.285 | N79: =(N73/N$67)*N68 -> 12748.492
B80: Inventory | F80: 8578 | G80: 9724 | H80: 9232 | I80: =(I74/I$67)*I69 -> 9308.6238 | J80: =(J74/J$67)*J69 -> 9293.0796 | K80: =(K74/K$67)*K69 -> 9665.4748 | L80: =(L74/L$67)*L69 -> 10054.182 | M80: =(M74/M$67)*M69 -> 10459.951 | N80: =(N74/N$67)*N69 -> 10883.569
B81: Accounts Payable | F81: 3095 | G81: 3344 | H81: 2678 | I81: =(I75/I$67)*I69 -> 2730.5297 | J81: =(J75/J$67)*J69 -> 2581.411 | K81: =(K75/K$67)*K69 -> 2684.8541 | L81: =(L75/L$67)*L69 -> 2792.8283 | M81: =(M75/M$67)*M69 -> 2905.542 | N81: =(N75/N$67)*N69 -> 3023.2137
B84: NET WORKING CAPITAL
B85: Current Assets | F85: =F79+F80 -> 19579 | G85: =G79+G80 -> 20949 | H85: =H79+H80 -> 20018 | I85: =I79+I80 -> 20075.225 | J85: =J79+J80 -> 20178.548 | K85: =K79+K80 -> 20987.149 | L85: =L79+L80 -> 21831.168 | M85: =M79+M80 -> 22712.237 | N85: =N79+N80 -> 23632.061
B86: Current Liabilities | F86: =F81 -> 3095 | G86: =G81 -> 3344 | H86: =H81 -> 2678 | I86: =I81 -> 2730.5297 | J86: =J81 -> 2581.411 | K86: =K81 -> 2684.8541 | L86: =L81 -> 2792.8283 | M86: =M81 -> 2905.542 | N86: =N81 -> 3023.2137
B87: Net Working Capital | F87: =F85-F86 -> 16484 | G87: =G85-G86 -> 17605 | H87: =H85-H86 -> 17340 | I87: =I85-I86 -> 17344.695 | J87: =J85-J86 -> 17597.137 | K87: =K85-K86 -> 18302.295 | L87: =L85-L86 -> 19038.34 | M87: =M85-M86 -> 19806.695 | N87: =N85-N86 -> 20608.847
B90: Cash from Working Capital Items | G90: =F87-G87 -> -1121 | H90: =G87-H87 -> 265 | I90: =H87-I87 -> -4.6952579 | J90: =I87-J87 -> -252.44136 | K90: =J87-K87 -> -705.15812 | L90: =K87-L87 -> -736.04536 | M90: =L87-M87 -> -768.35449 | N90: =M87-N87 -> -802.15274
N93: We have assumed working capital amounts per day in terminal year are equal to the previous year.
B97: Depreciation Schedule
B99: All figures in USD thousands unless stated | F99: =F64 -> 2023 | G99: =G64 -> 2024 | H99: =H64 -> 2025 | I99: =I64 -> 2026 | J99: =J64 -> 2027 | K99: =K64 -> 2028 | L99: =L64 -> 2029 | M99: =M64 -> 2030
B102: Capital Expenditure | F102: 904 | G102: 916 | H102: 1161 | I102: =Inputs!G35 -> 1091.6137 | J102: =Inputs!H35 -> 1135.1988 | K102: =Inputs!I35 -> 1180.6889 | L102: =Inputs!J35 -> 1228.1715 | M102: =Inputs!K35 -> 1277.7383
B105: EXISTING ASSET DEPRECIATION 1 | D105: Years | I105: Percent of Full Year
B106: Useful Life: Existing Assets | D106: =Inputs!L113 -> 12 | I106: 1 | J106: =I106+1 -> 2 | K106: =J106+1 -> 3 | L106: =K106+1 -> 4 | M106: =L106+1 -> 5
B107: =CONCATENATE("PP&E at End of ",H99) -> PP&E at End of 2025 | D107: =Inputs!L99 -> 7525 | I107: =MIN($D106-SUM($H107:H107),1) -> 1 | J107: =MIN($D106-SUM($H107:I107),1) -> 1 | K107: =MIN($D106-SUM($H107:J107),1) -> 1 | L107: =MIN($D106-SUM($H107:K107),1) -> 1 | M107: =MIN($D106-SUM($H107:L107),1) -> 1
B111: NEW ASSET DEPRECIATION 1 | D111: Years | I111: Percent of Full Year
B112: Useful Life: New Assets | D112: =Inputs!L114 -> 30 | I112: 1 | J112: =I112+1 -> 2 | K112: =J112+1 -> 3 | L112: =K112+1 -> 4 | M112: =L112+1 -> 5
B113: First Year Accounting Depreciation | D113: =Inputs!L112 -> 0.5 | I113: =IF(H113="",$D$113,MIN($D112-SUM($H113:H113),1)) -> 0.5 | J113: =IF(I113="",$D$113,MIN($D112-SUM($H113:I113),1)) -> 1 | K113: =IF(J113="",$D$113,MIN($D112-SUM($H113:J113),1)) -> 1 | L113: =IF(K113="",$D$113,MIN($D112-SUM($H113:K113),1)) -> 1 | M113: =IF(L113="",$D$113,MIN($D112-SUM($H113:L113),1)) -> 1
I115: Percent of Full Year
F116: Year | G116: Life | I116: =I$99 -> 2026 | J116: =J$99 -> 2027 | K116: =K$99 -> 2028 | L116: =L$99 -> 2029 | M116: =M$99 -> 2030
F117: =I99 -> 2026 | G117: =$D$112 -> 30 | I117: =I113 -> 0.5 | J117: =J113 -> 1 | K117: =K113 -> 1 | L117: =L113 -> 1 | M117: =M113 -> 1
F118: =F117+1 -> 2027 | G118: =$D$112 -> 30 | I118: =H117 -> 0 | J118: =I117 -> 0.5 | K118: =J117 -> 1 | L118: =K117 -> 1 | M118: =L117 -> 1
F119: =F118+1 -> 2028 | G119: =$D$112 -> 30 | I119: =H118 -> 0 | J119: =I118 -> 0 | K119: =J118 -> 0.5 | L119: =K118 -> 1 | M119: =L118 -> 1
F120: =F119+1 -> 2029 | G120: =$D$112 -> 30 | I120: =H119 -> 0 | J120: =I119 -> 0 | K120: =J119 -> 0 | L120: =K119 -> 0.5 | M120: =L119 -> 1
F121: =F120+1 -> 2030 | G121: =$D$112 -> 30 | I121: =H120 -> 0 | J121: =I120 -> 0 | K121: =J120 -> 0 | L121: =K120 -> 0 | M121: =L120 -> 0.5
F124: Year
F125: =F117 -> 2026 | G125: =SUMIF($I$99:$M$99,F125,$I$102:$M$102) -> 1091.6137 | H125: =G125/G117 -> 36.387124 | I125: =I117*$H125 -> 18.193562 | J125: =J117*$H125 -> 36.387124 | K125: =K117*$H125 -> 36.387124 | L125: =L117*$H125 -> 36.387124 | M125: =M117*$H125 -> 36.387124
F126: =F118 -> 2027 | G126: =SUMIF($I$99:$M$99,F126,$I$102:$M$102) -> 1135.1988 | H126: =G126/G118 -> 37.83996 | I126: =I118*$H126 -> 0 | J126: =J118*$H126 -> 18.91998 | K126: =K118*$H126 -> 37.83996 | L126: =L118*$H126 -> 37.83996 | M126: =M118*$H126 -> 37.83996
F127: =F119 -> 2028 | G127: =SUMIF($I$99:$M$99,F127,$I$102:$M$102) -> 1180.6889 | H127: =G127/G119 -> 39.356295 | I127: =I119*$H127 -> 0 | J127: =J119*$H127 -> 0 | K127: =K119*$H127 -> 19.678148 | L127: =L119*$H127 -> 39.356295 | M127: =M119*$H127 -> 39.356295
F128: =F120 -> 2029 | G128: =SUMIF($I$99:$M$99,F128,$I$102:$M$102) -> 1228.1715 | H128: =G128/G120 -> 40.939049 | I128: =I120*$H128 -> 0 | J128: =J120*$H128 -> 0 | K128: =K120*$H128 -> 0 | L128: =L120*$H128 -> 20.469524 | M128: =M120*$H128 -> 40.939049
F129: =F121 -> 2030 | G129: =SUMIF($I$99:$M$99,F129,$I$102:$M$102) -> 1277.7383 | H129: =G129/G121 -> 42.591278 | I129: =I121*$H129 -> 0 | J129: =J121*$H129 -> 0 | K129: =K121*$H129 -> 0 | L129: =L121*$H129 -> 0 | M129: =M121*$H129 -> 21.295639
B132: TOTAL ASSET DEPRECIATION 2
B133: Existing Assets | I133: =$D$107/$D$106*I107 -> 627.08333 | J133: =$D$107/$D$106*J107 -> 627.08333 | K133: =$D$107/$D$106*K107 -> 627.08333 | L133: =$D$107/$D$106*L107 -> 627.08333 | M133: =$D$107/$D$106*M107 -> 627.08333
B134: New Assets | I134: =SUM(I125:I129) -> 18.193562 | J134: =SUM(J125:J129) -> 55.307104 | K134: =SUM(K125:K129) -> 93.905232 | L134: =SUM(L125:L129) -> 134.0529 | M134: =SUM(M125:M129) -> 175.81807
B135: Total Depreciation | I135: =SUM(I133:I134) -> 645.2769 | J135: =SUM(J133:J134) -> 682.39044 | K135: =SUM(K133:K134) -> 720.98857 | L135: =SUM(L133:L134) -> 761.13624 | M135: =SUM(M133:M134) -> 802.9014
M138: All PP&E and capital expenditure is assumed depreciable (i.e. no land balance).
M139: This schedule calculates depreciation on a straight-line basis.
B143: Asset Schedule
B145: All figures in USD thousands unless stated | H145: =H99 -> 2025 | I145: =I99 -> 2026 | J145: =J99 -> 2027 | K145: =K99 -> 2028 | L145: =L99 -> 2029 | M145: =M99 -> 2030
B148: Capital Expenditure | I148: =I102 -> 1091.6137 | J148: =J102 -> 1135.1988 | K148: =K102 -> 1180.6889 | L148: =L102 -> 1228.1715 | M148: =M102 -> 1277.7383
B150: First Year Tax Depreciation | D150: =Inputs!L110 -> 0.5
B151: Blended Tax Depreciation Rate | D151: =Inputs!L111 -> 0.175
B154: PROPERTY PLANT & EQUIPMENT 1
B155: Beginning | I155: =H158 -> 7525 | J155: =I158 -> 7971.3368 | K155: =J158 -> 8424.1452 | L155: =K158 -> 8883.8455 | M155: =L158 -> 9350.8807
B156: Capital Expenditure | I156: =I148 -> 1091.6137 | J156: =J148 -> 1135.1988 | K156: =K148 -> 1180.6889 | L156: =L148 -> 1228.1715 | M156: =M148 -> 1277.7383
B157: Accounting Depreciation | I157: =-I135 -> -645.2769 | J157: =-J135 -> -682.39044 | K157: =-K135 -> -720.98857 | L157: =-L135 -> -761.13624 | M157: =-M135 -> -802.9014
B158: Ending | H158: =$D$107 -> 7525 | I158: =SUM(I155:I157) -> 7971.3368 | J158: =SUM(J155:J157) -> 8424.1452 | K158: =SUM(K155:K157) -> 8883.8455 | L158: =SUM(L155:L157) -> 9350.8807 | M158: =SUM(M155:M157) -> 9825.7177
B161: TAX BASIS 1
B162: Beginning | I162: =H165 -> 5382 | J162: =I165 -> 5436.2475 | K162: =J165 -> 5520.7731 | L162: =K165 -> 5632.0164 | M162: =L165 -> 5767.12
B163: Capital Expenditure | I163: =I148 -> 1091.6137 | J163: =J148 -> 1135.1988 | K163: =K148 -> 1180.6889 | L163: =L148 -> 1228.1715 | M163: =M148 -> 1277.7383
B164: Tax Depreciation | I164: =-(I162+I163*$D$150)*$D$151 -> -1037.3662 | J164: =-(J162+J163*$D$150)*$D$151 -> -1050.6732 | K164: =-(K162+K163*$D$150)*$D$151 -> -1069.4456 | L164: =-(L162+L163*$D$150)*$D$151 -> -1093.0679 | M164: =-(M162+M163*$D$150)*$D$151 -> -1121.0481
B165: Ending | H165: =Inputs!L100 -> 5382 | I165: =SUM(I162:I164) -> 5436.2475 | J165: =SUM(J162:J164) -> 5520.7731 | K165: =SUM(K162:K164) -> 5632.0164 | L165: =SUM(L162:L164) -> 5767.12 | M165: =SUM(M162:M164) -> 5923.8102
M168: Model assumes no dispositions that would impact the PP&E or the Tax Basis.
B172: Income Tax Schedule (Levered)
B174: All figures in USD thousands unless stated | H174: =H145 -> 2025 | I174: =I145 -> 2026 | J174: =J145 -> 2027 | K174: =K145 -> 2028 | L174: =L145 -> 2029 | M174: =M145 -> 2030
B177: Earnings Before Tax (EBT) | I177: =I52 -> 5530.3997 | J177: =J52 -> 5805.4865 | K177: =K52 -> 6093.2844 | L177: =L52 -> 6388.0014 | M177: =M52 -> 6690.2751
B178: Profitable Before Taxes? | I178: =IF(I188>0,1,0) -> 1 | J178: =IF(J188>0,1,0) -> 1 | K178: =IF(K188>0,1,0) -> 1 | L178: =IF(L188>0,1,0) -> 1 | M178: =IF(M188>0,1,0) -> 1
B180: Tax Rate | D180: =Inputs!L78 -> 0.175
B181: Unused Tax Losses Remaining? | D181: =IF(M199=0,0,1) -> 0
...
