Workbook

Sheet Growth Factors
B2: Growth variables
B4: EBITDA Variables | G4: Cash From WC
B5: Label | C5: Best | D5: Base | E5: Worst | G5: Label | H5: Best | I5: Base | J5: Worst
B6: Start | C6: 0.5 | D6: 0.55 | E6: 0.6 | G6: Start | H6: 0.9 | I6: 0.9 | J6: 0.9
B7: End | C7: 0.75 | D7: 0.55 | E7: 0.35 | G7: End | H7: 1.05 | I7: 0.9 | J7: 0.75
B8: Years | C8: 5 | D8: 5 | E8: 5 | G8: Years | H8: 5 | I8: 5 | J8: 5
B9: Increase | C9: =(C7-C6)/C8 -> 0.05 | D9: =(D7-D6)/D8 -> 0 | E9: =(E7-E6)/E8 -> -0.05 | G9: Increase | H9: =(H7-H6)/H8 -> 0.03 | I9: =(I7-I6)/I8 -> 0 | J9: =(J7-J6)/J8 -> -0.03
B15: % Growths for EBITDA
B16: Case and definition | I16: 2025 | J16: =I16+1 -> 2026 | K16: =J16+1 -> 2027 | L16: =K16+1 -> 2028 | M16: =L16+1 -> 2029 | N16: Term
I18: 1 | J18: =I18+1 -> 2 | K18: =J18+1 -> 3 | L18: =K18+1 -> 4 | M18: =L18+1 -> 5 | N18: =M18+1 -> 6
B19: Best | H19: =C6 -> 0.5 | I19: =H19+$C$9 -> 0.55 | J19: =I19+$C$9 -> 0.6 | K19: =J19+$C$9 -> 0.65 | L19: =K19+$C$9 -> 0.7 | M19: =L19+$C$9 -> 0.75 | N19: =M19 -> 0.75
I22: 1 | J22: =I22+1 -> 2 | K22: =J22+1 -> 3 | L22: =K22+1 -> 4 | M22: =L22+1 -> 5 | N22: =M22+1 -> 6
B23: Base | H23: =D6 -> 0.55 | I23: =H23+$D$9 -> 0.55 | J23: =I23+$D$9 -> 0.55 | K23: =J23+$D$9 -> 0.55 | L23: =K23+$D$9 -> 0.55 | M23: =L23+$D$9 -> 0.55 | N23: =M23+$D$9 -> 0.55
I26: 1 | J26: =I26+1 -> 2 | K26: =J26+1 -> 3 | L26: =K26+1 -> 4 | M26: =L26+1 -> 5 | N26: =M26+1 -> 6
B27: Worst | H27: =E6 -> 0.6 | I27: =H27+$E$9 -> 0.55 | J27: =I27+$E$9 -> 0.5 | K27: =J27+$E$9 -> 0.45 | L27: =K27+$E$9 -> 0.4 | M27: =L27+$E$9 -> 0.35 | N27: =M27 -> 0.35
B29: % Growths for Cash from WC
B30: Case and definition | I30: 2025 | J30: =I30+1 -> 2026 | K30: =J30+1 -> 2027 | L30: =K30+1 -> 2028 | M30: =L30+1 -> 2029 | N30: Term
I32: 1 | J32: =I32+1 -> 2 | K32: =J32+1 -> 3 | L32: =K32+1 -> 4 | M32: =L32+1 -> 5 | N32: =M32+1 -> 6
B33: Best | H33: =H6 -> 0.9 | I33: =H33+$H$9 -> 0.93 | J33: =I33+$H$9 -> 0.96 | K33: =J33+$H$9 -> 0.99 | L33: =K33+$H$9 -> 1.02 | M33: =L33+$H$9 -> 1.05 | N33: =M33 -> 1.05
I36: 1 | J36: =I36+1 -> 2 | K36: =J36+1 -> 3 | L36: =K36+1 -> 4 | M36: =L36+1 -> 5 | N36: =M36+1 -> 6
B37: Base | I37: =I6 -> 0.9 | J37: =I37 -> 0.9 | K37: =J37 -> 0.9 | L37: =K37 -> 0.9 | M37: =L37 -> 0.9 | N37: =M37 -> 0.9
I40: 1 | J40: =I40+1 -> 2 | K40: =J40+1 -> 3 | L40: =K40+1 -> 4 | M40: =L40+1 -> 5 | N40: =M40+1 -> 6
B41: Worst | H41: =J6 -> 0.9 | I41: =H41+$J$9 -> 0.87 | J41: =I41+$J$9 -> 0.84 | K41: =J41+$J$9 -> 0.81 | L41: =K41+$J$9 -> 0.78 | M41: =L41+$J$9 -> 0.75 | N41: =M41 -> 0.75
B43: Graph of Different Growths

Sheet Inputs
B1: #VALUE!
B2: Drivers
B4: Driver Switch | C4: 1 | H4: 2026 | I4: =H4+1 -> 2027 | J4: =I4+1 -> 2028 | K4: =J4+1 -> 2029 | L4: =K4+1 -> 2030 | M4: Term
B6: EBITDA Growth | H6: {=INDEX(H8:H10,$C$4)} -> 0.55 | I6: {=INDEX(I8:I10,$C$4)} -> 0.6 | J6: {=INDEX(J8:J10,$C$4)} -> 0.65 | K6: {=INDEX(K8:K10,$C$4)} -> 0.7 | L6: {=INDEX(L8:L10,$C$4)} -> 0.75 | M6: {=INDEX(M8:M10,$C$4)} -> 0.75
B8: Best | H8: ='Growth Factors'!I19 -> 0.55 | I8: ='Growth Factors'!J19 -> 0.6 | J8: ='Growth Factors'!K19 -> 0.65 | K8: ='Growth Factors'!L19 -> 0.7 | L8: ='Growth Factors'!M19 -> 0.75 | M8: ='Growth Factors'!N19 -> 0.75
B9: Base | H9: ='Growth Factors'!I23 -> 0.55 | I9: ='Growth Factors'!J23 -> 0.55 | J9: ='Growth Factors'!K23 -> 0.55 | K9: ='Growth Factors'!L23 -> 0.55 | L9: ='Growth Factors'!M23 -> 0.55 | M9: ='Growth Factors'!N23 -> 0.55
B10: Worst | H10: ='Growth Factors'!I27 -> 0.55 | I10: ='Growth Factors'!J27 -> 0.5 | J10: ='Growth Factors'!K27 -> 0.45 | K10: ='Growth Factors'!L27 -> 0.4 | L10: ='Growth Factors'!M27 -> 0.35 | M10: ='Growth Factors'!N27 -> 0.35
B12: Tax Depreciation | H12: {=INDEX(H14:H16,$C$4)} -> 6000 | I12: {=INDEX(I14:I16,$C$4)} -> 6000 | J12: {=INDEX(J14:J16,$C$4)} -> 6000 | K12: {=INDEX(K14:K16,$C$4)} -> 6000 | L12: {=INDEX(L14:L16,$C$4)} -> 6000 | M12: {=INDEX(M14:M16,$C$4)} -> 6000
B14: Best | H14: 6000 | I14: 6000 | J14: 6000 | K14: 6000 | L14: 6000 | M14: 6000
B15: Base | H15: 4000 | I15: 4000 | J15: 4000 | K15: 4000 | L15: 4000 | M15: 4000
B16: Worst | H16: 2000 | I16: 2000 | J16: 2000 | K16: 2000 | L16: 2000 | M16: 2000
B18: Cash from Working Capital | H18: {=INDEX(H20:H22,$C$4)} -> -11160 | I18: {=INDEX(I20:I22,$C$4)} -> -10713.6 | J18: {=INDEX(J20:J22,$C$4)} -> -10606.464 | K18: {=INDEX(K20:K22,$C$4)} -> -10818.593 | L18: {=INDEX(L20:L22,$C$4)} -> -11359.523 | M18: {=INDEX(M20:M22,$C$4)} -> -11927.499
B20: Best | G20: -12000 | H20: =G20*'Growth Factors'!I33 -> -11160 | I20: =H20*'Growth Factors'!J33 -> -10713.6 | J20: =I20*'Growth Factors'!K33 -> -10606.464 | K20: =J20*'Growth Factors'!L33 -> -10818.593 | L20: =K20*'Growth Factors'!M33 -> -11359.523 | M20: =L20*'Growth Factors'!N33 -> -11927.499
B21: Base | G21: -10000 | H21: =G21*'Growth Factors'!I37 -> -9000 | I21: =H21*'Growth Factors'!J37 -> -8100 | J21: =I21*'Growth Factors'!K37 -> -7290 | K21: =J21*'Growth Factors'!L37 -> -6561 | L21: =K21*'Growth Factors'!M37 -> -5904.9 | M21: =L21*'Growth Factors'!N37 -> -5314.41
B22: Worst | G22: -8000 | H22: =G22*'Growth Factors'!I41 -> -6960 | I22: =H22*'Growth Factors'!J41 -> -5846.4 | J22: =I22*'Growth Factors'!K41 -> -4735.584 | K22: =J22*'Growth Factors'!L41 -> -3693.7555 | L22: =K22*'Growth Factors'!M41 -> -2770.3166 | M22: =L22*'Growth Factors'!N41 -> -2077.7375
B24: Other Inputs
B26: Label | F26: Value
B27: Current Share Price | F27: {=_FV(B1,"Price")} -> 176.97
B28: Outstanding Shares | F28: {=_FV(B1,"Shares outstanding",TRUE)/1000000} -> 24300
B29: Net Debt (Net cash) | F29: 16300
B30: Cost of Equity | F30: 0.16
B32: Capital Structure | I32: Cost of Debt
E34: Current | F34: Target | I34: Pre-Tax Cost of Debt | M34: 0.048009368
B35: Total Debt | D35: 8463 | E35: =D35/D37 -> 0.0019641044 | F35: 0.002 | I35: Tax Rate | M35: 0.1468
B36: Market Capitalization | D36: {=_FV(B1,"Market cap",TRUE)/1000000} -> 4300371 | E36: =D36/D37 -> 0.9980359 | F36: =F37-F35 -> 0.998 | I36: After-Tax Cost of Debt | M36: =M34*(1-M35) -> 0.040961593
B37: Total Capitalization | D37: =SUM(D35:D36) -> 4308834 | E37: =SUM(E35:E36) -> 1 | F37: =E37 -> 1
B39: Debt / Equity | E39: =E35/E36 -> 0.0019679697 | F39: =F35/F36 -> 0.002004008 | I39: Weighted Average Cost of Capital
L41: Weight | M41: Cost
I42: Debt Capital | L42: =F35 -> 0.002 | M42: =M36 -> 0.040961593
I43: Equity Capital | L43: =F36 -> 0.998 | M43: =F30 -> 0.16
I46: Weighted Average Cost of Capital | M46: =L42*M42+L43*M43 -> 0.15976192

Sheet Sheet1
A1: 115400 | B1: 97858 | C1: 44301 | D1: 15356 | E1: 17475 | F1: 10557
B2: =A1/B1-1 -> 0.17925974 | C2: =B1/C1-1 -> 1.2089343 | D2: =C1/D1-1 -> 1.884931 | E2: =D1/E1-1 -> -0.12125894 | F2: =E1/F1-1 -> 0.6552998
B4: =AVERAGE(B2:F2) -> 0.76143318
B5: Fiscal Year | C5: EBITDA ($B)
B6: 2013 | C6: 0.6 | D6: =C7/C6-1 -> 0.23333333 | G6: Fiscal Year | H6: End Date | I6: Change in Working Capital ($M)
B7: 2014 | C7: 0.74 | D7: =C8/C7-1 -> -0.067567568 | G7: 2013 | H7: 45684 | I7: -112 | J7: =I7*-1 -> 112 | K7: =J8/J7-1 -> -1.1071429
B8: 2015 | C8: 0.69 | D8: =C9/C8-1 -> 0.71014493 | G8: 2014 | H8: 45683 | I8: 12 | J8: =I8*-1 -> -12 | K8: =J9/J8-1 -> -17.916667
B9: 2016 | C9: 1.18 | D9: =C10/C9-1 -> 0.72033898 | G9: 2015 | H9: 45682 | I9: -203 | J9: =I9*-1 -> 203 | K9: =J10/J9-1 -> -0.74876847
B10: 2017 | C10: 2.03 | D10: =C11/C10-1 -> 0.87192118 | G10: 2016 | H10: 45688 | I10: -51 | J10: =I10*-1 -> 51 | K10: =J11/J10-1 -> 12.313725
B11: 2018 | C11: 3.8 | D11: =C12/C11-1 -> 0.10526316 | G11: 2017 | H11: 45686 | I11: -679 | J11: =I11*-1 -> 679 | K11: =J12/J11-1 -> -1.2724595
B12: 2019 | C12: 4.2 | D12: =C13/C12-1 -> -0.095238095 | G12: 2018 | H12: 45685 | I12: 185 | J12: =I12*-1 -> -185 | K12: =J13/J12-1 -> -5.6324324
B13: 2020 | C13: 3.8 | D13: =C14/C13-1 -> 0.40263158 | G13: 2019 | H13: 45684 | I13: -857 | J13: =I13*-1 -> 857 | K13: =J14/J13-1 -> -1.8366394
B14: 2021 | C14: 5.33 | D14: =C15/C14-1 -> 1.1294559 | G14: 2020 | H14: 45683 | I14: 717 | J14: =I14*-1 -> -717 | K14: =J15/J14-1 -> -1.9804742
B15: 2022 | C15: 11.35 | D15: =C16/C15-1 -> -0.4722467 | G15: 2021 | H15: 45688 | I15: -703 | J15: =I15*-1 -> 703 | K15: =J16/J15-1 -> 3.7837838
B16: 2023 | C16: 5.99 | D16: =C17/C16-1 -> 4.9398998 | G16: 2022 | H16: 45687 | I16: -3363 | J16: =I16*-1 -> 3363 | K16: =J17/J16-1 -> -0.34374071
B17: 2024 | C17: 35.58 | D17: =C18/C17-1 -> 1.421023 | G17: 2023 | H17: 45686 | I17: -2207 | J17: =I17*-1 -> 2207 | K17: =J18/J17-1 -> 0.6864522
B18: 2025 | C18: 86.14 | G18: 2024 | H18: 45685 | I18: -3722 | J18: =I18*-1 -> 3722 | K18: =J19/J18-1 -> 1.5209565
C19: =AVERAGE(C6:C18) -> 12.417692 | G19: 2025 | H19: 45683 | I19: -9383 | J19: =I19*-1 -> 9383
C20: =(C18-C6)^(1/12)-1 -> 0.4488189 | D20: =AVERAGE(D6:D18) -> 0.8249133 | I20: =(I19-I7)^(1/12)-1 -> #NUM! | J20: =(J19-J7)^(1/12)-1 -> 1.1408877 | K20: =AVERAGE(K7:K18) -> -1.0444505

Sheet Compact DCF
B1: =Inputs!B1 -> #VALUE!
B2: Unlevered Free Cash Flow Schedule
B4: All figures in USD Millions unless stated | H4: =I4-1 -> 2023 | I4: =J4-1 -> 2024 | J4: 2025 | K4: 2026 | L4: =K4+1 -> 2027 | M4: =L4+1 -> 2028 | N4: =M4+1 -> 2029 | O4: =N4+1 -> 2030 | P4: Term
C7: PROFIT METRICS
C9: EBITDA Growth | I9: =I10/H10-1 -> 3.8426966 | J9: =J10/I10-1 -> 1.4164733 | K9: =Inputs!H6 -> 0.55 | L9: =Inputs!I6 -> 0.6 | M9: =Inputs!J6 -> 0.65 | N9: =Inputs!K6 -> 0.7 | O9: =Inputs!L6 -> 0.75 | P9: =Inputs!M6 -> 0.75
C10: EBITDA | H10: 7120 | I10: 34480 | J10: 83320 | K10: =J10*(1+K9) -> 129146 | L10: =K10*(1+L9) -> 206633.6 | M10: =L10*(1+M9) -> 340945.44 | N10: =M10*(1+N9) -> 579607.25 | O10: =N10*(1+O9) -> 1014312.7 | P10: =O10*(1+P9) -> 1775047.2
C12: Tax Depreciation | H12: =H10-H13 -> 1540 | I12: =I10-I13 -> 1510 | J12: =J10-J13 -> 1870 | K12: =Inputs!H12 -> 6000 | L12: =Inputs!I12 -> 6000 | M12: =Inputs!J12 -> 6000 | N12: =Inputs!K12 -> 6000 | O12: =Inputs!L12 -> 6000 | P12: =Inputs!M12 -> 6000
C13: Operating Profit | H13: 5580 | I13: 32970 | J13: 81450 | K13: =K10-K12 -> 123146 | L13: =L10-L12 -> 200633.6 | M13: =M10-M12 -> 334945.44 | N13: =N10-N12 -> 573607.25 | O13: =O10-O12 -> 1008312.7 | P13: =P10-P12 -> 1769047.2
C15: Tax Rate | H15: =H16/H13 -> 0.35430108 | I15: =I16/I13 -> 0.19857446 | J15: =J16/J13 -> 0.19181093 | K15: 0.2 | L15: =K15 -> 0.2 | M15: =L15 -> 0.2 | N15: =M15 -> 0.2 | O15: =N15 -> 0.2 | P15: =O15 -> 0.2
C16: Current Tax | H16: 1977 | I16: 6547 | J16: 15623 | K16: =K13*K15 -> 24629.2 | L16: =L13*L15 -> 40126.72 | M16: =M13*M15 -> 66989.088 | N16: =N13*N15 -> 114721.45 | O16: =O13*O15 -> 201662.54 | P16: =P13*P15 -> 353809.44
C21: UNLEVERED FREE CASH FLOW
C23: EBITDA | K23: =K10 -> 129146 | L23: =L10 -> 206633.6 | M23: =M10 -> 340945.44 | N23: =N10 -> 579607.25 | O23: =O10 -> 1014312.7 | P23: =P10 -> 1775047.2
C24: Current Taxes | K24: {=-K16:P16} -> -24629.2 | L24: -40126.72 | M24: -66989.088 | N24: -114721.45 | O24: -201662.54 | P24: -353809.44
C25: Capital Expenditure 1 | K25: =-K12 -> -6000 | L25: =-L12 -> -6000 | M25: =-M12 -> -6000 | N25: =-N12 -> -6000 | O25: =-O12 -> -6000 | P25: =-P12 -> -6000
C26: Cash from Working Capital | K26: =Inputs!H18 -> -11160 | L26: =Inputs!I18 -> -10713.6 | M26: =Inputs!J18 -> -10606.464 | N26: =Inputs!K18 -> -10818.593 | O26: =Inputs!L18 -> -11359.523 | P26: =Inputs!M18 -> -11927.499
C27: Unlevered Free Cash Flow | K27: =SUM(K23:K26) -> 87356.8 | L27: =SUM(L23:L26) -> 149793.28 | M27: =SUM(M23:M26) -> 257349.89 | N27: =SUM(N23:N26) -> 448067.21 | O27: =SUM(O23:O26) -> 795290.62 | P27: =SUM(P23:P26) -> 1403310.3
P31: Capital expenditure has been set equal to tax depreciation.
B35: Discounted Cash Flow Schedule
B37: All figures in USD thousands unless stated | J37: Valuation | K37: Discrete Forecast | P37: Term
J38: (YY-MM-DD) | K38: (YY-MM-DD) | L38: (YY-MM-DD) | M38: (YY-MM-DD) | N38: (YY-MM-DD) | O38: (YY-MM-DD) | P38: (YY-MM-DD)
J39: =DATE(G47,1,1) -> 45658 | K39: =DATE(G47,12,31) -> 46022 | L39: =EDATE(K39,12) -> 46387 | M39: =EDATE(L39,12) -> 46752 | N39: =EDATE(M39,12) -> 47118 | O39: =EDATE(N39,12) -> 47483 | P39: =EDATE(O39,12) -> 47848
K42: UNLEVERED FREE CASH FLOW
K43: =K27 -> 87356.8 | L43: =L27 -> 149793.28 | M43: =M27 -> 257349.89 | N43: =N27 -> 448067.21 | O43: =O27 -> 795290.62 | P43: =P27 -> 1403310.3
D46: ASSUMPTIONS | K46: CASH FLOW PROFILES
D47: First Year of Forecast | G47: 2025 | I47: Discrete Forecast | K47: =K43 -> 87356.8 | L47: =L43 -> 149793.28 | M47: =M43 -> 257349.89 | N47: =N43 -> 448067.21 | O47: =O43 -> 795290.62
D48: Terminal Growth Rate | G48: 0.02 | I48: Terminal Value 2 | K48: 0 | L48: 0 | M48: 0 | N48: 0 | O48: =P43/(G49-G48) -> 10040719
D49: WACC 1 | G49: =Inputs!M46 -> 0.15976192 | I49: Total Cash Flow | K49: =SUM(K47:K48) -> 87356.8 | L49: =SUM(L47:L48) -> 149793.28 | M49: =SUM(M47:M48) -> 257349.89 | N49: =SUM(N47:N48) -> 448067.21 | O49: =SUM(O47:O48) -> 10836010
D54: ENTERPRISE VALUE | K54: EQUITY VALUE PER SHARE
D55: PV of Discrete | F55: =NPV(G49,K47:O47) -> 978368.11 | G55: =F55/F57 -> 0.16974377 | K55: Equity Value | N55: =G64 -> 5747494.1
D56: PV of Terminal | F56: =NPV(G49,K48:O48) -> 4785426 | G56: =F56/F57 -> 0.83025623 | K56: Shares Outstanding | M56: (FD 000) | N56: =Inputs!F28 -> 24300 | O56: 24300
D57: Enterprise Value | F57: =SUM(F55:F56) -> 5763794.1 | G57: =SUM(G55:G56) -> 1 | K57: Equity Value | M57: (USD/sh) | N57: =N55/N56 -> 236.52239
D61: EQUITY VALUE | K61: PREMIUM (DISCOUNT)
D62: Enterprise Value | G62: =F57 -> 5763794.1 | K62: Equity Value | M62: (USD/sh) | N62: =N57 -> 236.52239
D63: Less: Net Debt | G63: =-Inputs!F29 -> -16300 | K63: Current Price | M63: (USD/sh) | N63: =Inputs!F27 -> 176.97
D64: Equity Value | G64: =SUM(G62:G63) -> 5747494.1 | K64: Premium (Discount) | N64: =N62/N63-1 -> 0.33651122
N68: WACC = Weighted Average Cost of Capital.
N69: The growing perpetuity method was used to calculate the terminal value.
B73: Sensitivity Analysis
B75: All figures in USD thousands unless stated
D78: Terminal Growth Rate | G78: =G48 -> 0.02 | K78: Shares Outstanding | M78: (FD 000) | N78: =N56 -> 24300
D79: WACC 1 | G79: =G49 -> 0.15976192 | K79: Current Price | M79: ($/sh) | N79: =N63 -> 176.97
D80: Enterprise Value | G80: =F57 -> 5763794.1
D81: Net Debt | G81: =-G63 -> 16300
D85: ENTERPRISE VALUE 2 | K85: EQUITY VALUE PER SHARE
D87: Terminal Growth Rate | K87: Terminal Growth Rate
C88: =G80 -> 5763794.1 | D88: =E88-0.005 -> 0.015 | E88: =F88-0.005 -> 0.02 | F88: 0.025 | G88: =F88+0.005 -> 0.03 | H88: =G88+0.005 -> 0.035 | K88: {=D88:H88} -> 0.015 | L88: 0.02 | M88: 0.025 | N88: 0.03 | O88: 0.035
B89: WACC | C89: =C90-0.01 -> 0.13 | D89: 7702568.8 | E89: 8003620.4 | F89: 8333343.6 | G89: 8696039.2 | H89: 9096913.1 | I89: WACC | J89: =C89 -> 0.13 | K89: =D101/$N$78 -> 316.30736 | L89: =E101/$N$78 -> 328.69631 | M89: =F101/$N$78 -> 342.26517 | N89: =G101/$N$78 -> 357.19091 | O89: =H101/$N$78 -> 373.68778
C90: =C91-0.01 -> 0.14 | D90: 6874617.5 | E90: 7117562.6 | F90: 7381633.4 | G90: 7669710.6 | H90: 7985223.7 | J90: =C90 -> 0.14 | K90: =D102/$N$78 -> 282.23529 | L90: =E102/$N$78 -> 292.23303 | M90: =F102/$N$78 -> 303.10014 | N90: =G102/$N$78 -> 314.95517 | O90: =H102/$N$78 -> 327.93925
C91: 0.15 | D91: 6178121.2 | E91: 6376894.1 | F91: 6591569 | G91: 6824133.4 | H91: 7076920.8 | J91: =C91 -> 0.15 | K91: =D103/$N$78 -> 253.57289 | L91: =E103/$N$78 -> 261.75285 | M91: =F103/$N$78 -> 270.5872 | N91: =G103/$N$78 -> 280.15775 | O91: =H103/$N$78 -> 290.56053
C92: =C91+0.01 -> 0.16 | D92: 5585435.9 | E92: 5750001 | F92: 5926756.1 | G92: 6117107.8 | H92: 6322687.6 | J92: =C92 -> 0.16 | K92: =D104/$N$78 -> 229.18255 | L92: =E104/$N$78 -> 235.95477 | M92: =F104/$N$78 -> 243.22865 | N92: =G104/$N$78 -> 251.06205 | O92: =H104/$N$78 -> 259.52212
C93: =C92+0.01 -> 0.17 | D93: 5076078.2 | E93: 5213726.7 | F93: 5360868.2 | G93: 5518519.8 | H93: 5687849.3 | J93: =C93 -> 0.17 | K93: =D105/$N$78 -> 208.22133 | L93: =E105/$N$78 -> 213.88587 | M93: =F105/$N$78 -> 219.94108 | N93: =G105/$N$78 -> 226.4288 | O93: =H105/$N$78 -> 233.39709
D97: EQUITY VALUE | K97: PREMIUM (DISCOUNT) TO CURRENT PRICE
D99: Terminal Growth Rate | K99: Terminal Growth Rate
D100: =D88 -> 0.015 | E100: =E88 -> 0.02 | F100: =F88 -> 0.025 | G100: =G88 -> 0.03 | H100: =H88 -> 0.035 | K100: =K88 -> 0.015 | L100: =L88 -> 0.02 | M100: =M88 -> 0.025 | N100: =N88 -> 0.03 | O100: =O88 -> 0.035
B101: WACC | C101: =C89 -> 0.13 | D101: =D89-$G$81 -> 7686268.8 | E101: =E89-$G$81 -> 7987320.4 | F101: =F89-$G$81 -> 8317043.6 | G101: =G89-$G$81 -> 8679739.2 | H101: =H89-$G$81 -> 9080613.1 | I101: WACC | J101: =J89 -> 0.13 | K101: =K89/$N$79-1 -> 0.78735017 | L101: =L89/$N$79-1 -> 0.85735613 | M101: =M89/$N$79-1 -> 0.93402933 | N101: =N89/$N$79-1 -> 1.0183698 | O101: =O89/$N$79-1 -> 1.1115883
C102: =C90 -> 0.14 | D102: =D90-$G$81 -> 6858317.5 | E102: =E90-$G$81 -> 7101262.6 | F102: =F90-$G$81 -> 7365333.4 | G102: =G90-$G$81 -> 7653410.6 | H102: =H90-$G$81 -> 7968923.7 | J102: =J90 -> 0.14 | K102: =K90/$N$79-1 -> 0.59481995 | L102: =L90/$N$79-1 -> 0.65131394 | M102: =M90/$N$79-1 -> 0.71272045 | N102: =N90/$N$79-1 -> 0.77970938 | O102: =O90/$N$79-1 -> 0.8530782
C103: =C91 -> 0.15 | D103: =D91-$G$81 -> 6161821.2 | E103: =E91-$G$81 -> 6360594.1 | F103: =F91-$G$81 -> 6575269 | G103: =G91-$G$81 -> 6807833.4 | H103: =H91-$G$81 -> 7060620.8 | J103: =J91 -> 0.15 | K103: =K91/$N$79-1 -> 0.43285804 | L103: =L91/$N$79-1 -> 0.47908033 | M103: =M91/$N$79-1 -> 0.5290004 | N103: =N91/$N$79-1 -> 0.58308048 | O103: =O91/$N$79-1 -> 0.64186317
C104: =C92 -> 0.16 | D104: =D92-$G$81 -> 5569135.9 | E104: =E92-$G$81 -> 5733701 | F104: =F92-$G$81 -> 5910456.1 | G104: =G92-$G$81 -> 6100807.8 | H104: =H92-$G$81 -> 6306387.6 | J104: =J92 -> 0.16 | K104: =K92/$N$79-1 -> 0.29503616 | L104: =L92/$N$79-1 -> 0.33330381 | M104: =M92/$N$79-1 -> 0.3744061 | N104: =N92/$N$79-1 -> 0.4186701 | O104: =O92/$N$79-1 -> 0.46647523
C105: =C93 -> 0.17 | D105: =D93-$G$81 -> 5059778.2 | E105: =E93-$G$81 -> 5197426.7 | F105: =F93-$G$81 -> 5344568.2 | G105: =G93-$G$81 -> 5502219.8 | H105: =H93-$G$81 -> 5671549.3 | J105: =J93 -> 0.17 | K105: =K93/$N$79-1 -> 0.1765911 | L105: =L93/$N$79-1 -> 0.20859961 | M105: =M93/$N$79-1 -> 0.24281561 | N105: =N93/$N$79-1 -> 0.27947561 | O105: =O93/$N$79-1 -> 0.31885116
O108: WACC = Weighted Average Cost of Capital.
O109: This table requires the workbook calculation to be set to automatic to update.

Sheet Compact DCF on Actuals
B1: =Inputs!B1 -> #VALUE!
B2: Unlevered Free Cash Flow Schedule
B4: All figures in USD Millions unless stated | K4: 2013 | L4: =K4+1 -> 2014 | M4: =L4+1 -> 2015 | N4: =M4+1 -> 2016 | O4: =N4+1 -> 2017 | P4: Term
C7: PROFIT METRICS
C9: EBITDA | K9: 874 | L9: 740 | M9: 1007 | N9: 973 | O9: 2121 | P9: =O9 -> 2121
C11: Tax Depreciation | K11: =K9-K12 -> 226 | L11: =L9-L12 -> 244 | M11: =M9-M12 -> 248 | N11: =N9-N12 -> 226 | O11: =O9-O12 -> 187 | P11: =O11 -> 187
C12: Operating Profit | K12: 648 | L12: 496 | M12: 759 | N12: 747 | O12: 1934 | P12: =P9-P11 -> 1934
C14: Tax Rate | K14: 0.104 | L14: 0.04 | M14: 0.147 | N14: 0.172 | O14: 0.238 | P14: =O14 -> 0.238
C15: Current Tax | K15: =K12*K14 -> 67.392 | L15: =L12*L14 -> 19.84 | M15: =M12*M14 -> 111.573 | N15: =N12*N14 -> 128.484 | O15: =O12*O14 -> 460.292 | P15: =P12*P14 -> 460.292
C20: UNLEVERED FREE CASH FLOW
C22: EBITDA | K22: =K9 -> 874 | L22: =L9 -> 740 | M22: =M9 -> 1007 | N22: =N9 -> 973 | O22: =O9 -> 2121 | P22: =P9 -> 2121
C23: Current Taxes | K23: {=-K15:P15} -> -67.392 | L23: -19.84 | M23: -111.573 | N23: -128.484 | O23: -460.292 | P23: -460.292
C24: Capital Expenditure 1 | K24: =-K11 -> -226 | L24: =-L11 -> -244 | M24: =-M11 -> -248 | N24: =-N11 -> -226 | O24: =-O11 -> -187 | P24: =-P11 -> -187
C25: Cash from Working Capital | K25: -112 | L25: 12 | M25: -203 | N25: -51 | O25: -679 | P25: =O25 -> -679
C26: Unlevered Free Cash Flow | K26: =SUM(K22:K25) -> 468.608 | L26: =SUM(L22:L25) -> 488.16 | M26: =SUM(M22:M25) -> 444.427 | N26: =SUM(N22:N25) -> 567.516 | O26: =SUM(O22:O25) -> 794.708 | P26: =SUM(P22:P25) -> 794.708
P30: Capital expenditure has been set equal to tax depreciation.
B34: Discounted Cash Flow Schedule
B36: All figures in USD thousands unless stated | J36: Valuation | K36: Discrete Forecast | P36: Term
J37: (YY-MM-DD) | K37: (YY-MM-DD) | L37: (YY-MM-DD) | M37: (YY-MM-DD) | N37: (YY-MM-DD) | O37: (YY-MM-DD) | P37: (YY-MM-DD)
J38: =DATE(G46,1,1) -> 41275 | K38: =DATE(G46,12,31) -> 41639 | L38: =EDATE(K38,12) -> 42004 | M38: =EDATE(L38,12) -> 42369 | N38: =EDATE(M38,12) -> 42735 | O38: =EDATE(N38,12) -> 43100 | P38: =EDATE(O38,12) -> 43465
K41: UNLEVERED FREE CASH FLOW
K42: =K26 -> 468.608 | L42: =L26 -> 488.16 | M42: =M26 -> 444.427 | N42: =N26 -> 567.516 | O42: =O26 -> 794.708 | P42: =P26 -> 794.708
D45: ASSUMPTIONS | K45: CASH FLOW PROFILES
D46: First Year of Forecast | G46: 2013 | I46: Discrete Forecast | K46: =K42 -> 468.608 | L46: =L42 -> 488.16 | M46: =M42 -> 444.427 | N46: =N42 -> 567.516 | O46: =O42 -> 794.708
D47: Terminal Growth Rate | G47: 0.02 | I47: Terminal Value 2 | K47: 0 | L47: 0 | M47: 0 | N47: 0 | O47: =P42/(G48-G47) -> 10320.883
D48: WACC 1 | G48: 0.097 | I48: Total Cash Flow | K48: =SUM(K46:K47) -> 468.608 | L48: =SUM(L46:L47) -> 488.16 | M48: =SUM(M46:M47) -> 444.427 | N48: =SUM(N46:N47) -> 567.516 | O48: =SUM(O46:O47) -> 11115.591
D53: ENTERPRISE VALUE | K53: EQUITY VALUE PER SHARE
D54: PV of Discrete | F54: =NPV(G48,K46:O46) -> 2061.5855 | G54: =F54/F56 -> 0.2408915 | K54: Equity Value | N54: =G63 -> 4458.1495
D55: PV of Terminal | F55: =NPV(G48,K47:O47) -> 6496.564 | G55: =F55/F56 -> 0.7591085 | K55: Shares Outstanding | M55: (FD 000) | N55: 631
D56: Enterprise Value | F56: =SUM(F54:F55) -> 8558.1495 | G56: =SUM(G54:G55) -> 1 | K56: Equity Value | M56: (USD/sh) | N56: =N54/N55 -> 7.0652131
D60: EQUITY VALUE | K60: PREMIUM (DISCOUNT)
D61: Enterprise Value | G61: =F56 -> 8558.1495 | K61: Equity Value 3 | M61: (USD/sh) | N61: =N56 -> 7.0652131 | O61: 'The actual equity value for the year of 2018 had a High of $7.32/share
D62: Less: Net Debt | G62: -4100 | K62: Current Price | M62: (USD/sh) | N62: 0.4 | O62: This was the share price in 2013
D63: Equity Value | G63: =SUM(G61:G62) -> 4458.1495 | K63: Premium (Discount) | N63: =N61/N62-1 -> 16.663033
N67: WACC = Weighted Average Cost of Capital.
N68: The growing perpetuity method was used to calculate the terminal value.
B72: Sensitivity Analysis
B74: All figures in USD thousands unless stated
D77: Terminal Growth Rate | G77: =G47 -> 0.02 | K77: Shares Outstanding | M77: (FD 000) | N77: =N55 -> 631
D78: WACC 1 | G78: =G48 -> 0.097 | K78: Current Price | M78: ($/sh) | N78: =N62 -> 0.4
D79: Enterprise Value | G79: =F56 -> 8558.1495
D80: Net Debt | G80: =-G62 -> 4100
D84: ENTERPRISE VALUE 2 | K84: EQUITY VALUE PER SHARE
D86: Terminal Growth Rate | K86: Terminal Growth Rate
C87: =G79 -> 8558.1495 | D87: =E87-0.005 -> 0.015 | E87: =F87-0.005 -> 0.02 | F87: 0.025 | G87: =F87+0.005 -> 0.03 | H87: =G87+0.005 -> 0.035 | K87: {=D87:H87} -> 0.015 | L87: 0.02 | M87: 0.025 | N87: 0.03 | O87: 0.035
B88: WACC | C88: =C89-0.01 -> 0.079880848 | D88: 10504.841 | E88: 11201.297 | F88: 12024.657 | G88: 13013.082 | H88: 14221.74 | I88: WACC | J88: =C88 -> 0.079880848 | K88: =D100/$N$77 -> 10.150303 | L88: =E100/$N$77 -> 11.254037 | M88: =F100/$N$77 -> 12.558886 | N88: =G100/$N$77 -> 14.125328 | O88: =H100/$N$77 -> 16.040793
C89: =C90-0.01 -> 0.089880848 | D89: 9004.6971 | E89: 9498.4999 | F89: 10068.412 | G89: 10733.498 | H89: 11519.772 | J89: =C89 -> 0.089880848 | K89: =D101/$N$77 -> 7.7728956 | L89: =E101/$N$77 -> 8.5554674 | M89: =F101/$N$77 -> 9.458656 | N89: =G101/$N$77 -> 10.512676 | O89: =H101/$N$77 -> 11.758751
C90: 0.099880848 | D90: 7861.7059 | E90: 8225.786 | F90: 8638.4874 | G90: 9110.2467 | H90: 9654.7177 | J90: =C90 -> 0.099880848 | K90: =D102/$N$77 -> 5.961499 | L90: =E102/$N$77 -> 6.5384881 | M90: =F102/$N$77 -> 7.1925316 | N90: =G102/$N$77 -> 7.9401691 | O90: =H102/$N$77 -> 8.8030391
C91: =C90+0.01 -> 0.10988085 | D91: 6962.7714 | E91: 7239.4338 | F91: 7548.6904 | G91: 7896.6617 | H91: 8291.103 | J91: =C91 -> 0.10988085 | K91: =D103/$N$77 -> 4.5368803 | L91: =E103/$N$77 -> 4.9753309 | M91: =F103/$N$77 -> 5.4654364 | N91: =G103/$N$77 -> 6.0168965 | O91: =H103/$N$77 -> 6.6420015
C92: =C91+0.01 -> 0.11988085 | D92: 6237.9403 | E92: 6453.288 | F92: 6691.3322 | G92: 6955.8609 | H92: 7251.5543 | J92: =C92 -> 0.11988085 | K92: =D104/$N$77 -> 3.388178 | L92: =E104/$N$77 -> 3.7294579 | M92: =F104/$N$77 -> 4.1067072 | N92: =G104/$N$77 -> 4.5259285 | O92: =H104/$N$77 -> 4.9945393
D96: EQUITY VALUE | K96: PREMIUM (DISCOUNT) TO CURRENT PRICE
D98: Terminal Growth Rate | K98: Terminal Growth Rate
D99: =D87 -> 0.015 | E99: =E87 -> 0.02 | F99: =F87 -> 0.025 | G99: =G87 -> 0.03 | H99: =H87 -> 0.035 | K99: =K87 -> 0.015 | L99: =L87 -> 0.02 | M99: =M87 -> 0.025 | N99: =N87 -> 0.03 | O99: =O87 -> 0.035
B100: WACC | C100: =C88 -> 0.079880848 | D100: =D88-$G$80 -> 6404.841 | E100: =E88-$G$80 -> 7101.2974 | F100: =F88-$G$80 -> 7924.6571 | G100: =G88-$G$80 -> 8913.0822 | H100: =H88-$G$80 -> 10121.74 | I100: WACC | J100: =J88 -> 0.079880848 | K100: =K88/$N$78-1 -> 24.375757 | L100: =L88/$N$78-1 -> 27.135093 | M100: =M88/$N$78-1 -> 30.397215 | N100: =N88/$N$78-1 -> 34.313321 | O100: =O88/$N$78-1 -> 39.101982
C101: =C89 -> 0.089880848 | D101: =D89-$G$80 -> 4904.6971 | E101: =E89-$G$80 -> 5398.4999 | F101: =F89-$G$80 -> 5968.4119 | G101: =G89-$G$80 -> 6633.4983 | H101: =H89-$G$80 -> 7419.7719 | J101: =J89 -> 0.089880848 | K101: =K89/$N$78-1 -> 18.432239 | L101: =L89/$N$78-1 -> 20.388669 | M101: =M89/$N$78-1 -> 22.64664 | N101: =N89/$N$78-1 -> 25.281689 | O101: =O89/$N$78-1 -> 28.396878
C102: =C90 -> 0.099880848 | D102: =D90-$G$80 -> 3761.7059 | E102: =E90-$G$80 -> 4125.786 | F102: =F90-$G$80 -> 4538.4874 | G102: =G90-$G$80 -> 5010.2467 | H102: =H90-$G$80 -> 5554.7177 | J102: =J90 -> 0.099880848 | K102: =K90/$N$78-1 -> 13.903747 | L102: =L90/$N$78-1 -> 15.34622 | M102: =M90/$N$78-1 -> 16.981329 | N102: =N90/$N$78-1 -> 18.850423 | O102: =O90/$N$78-1 -> 21.007598
C103: =C91 -> 0.10988085 | D103: =D91-$G$80 -> 2862.7714 | E103: =E91-$G$80 -> 3139.4338 | F103: =F91-$G$80 -> 3448.6904 | G103: =G91-$G$80 -> 3796.6617 | H103: =H91-$G$80 -> 4191.103 | J103: =J91 -> 0.10988085 | K103: =K91/$N$78-1 -> 10.342201 | L103: =L91/$N$78-1 -> 11.438327 | M103: =M91/$N$78-1 -> 12.663591 | N103: =N91/$N$78-1 -> 14.042241 | O103: =O91/$N$78-1 -> 15.605004
C104: =C92 -> 0.11988085 | D104: =D92-$G$80 -> 2137.9403 | E104: =E92-$G$80 -> 2353.288 | F104: =F92-$G$80 -> 2591.3322 | G104: =G92-$G$80 -> 2855.8609 | H104: =H92-$G$80 -> 3151.5543 | J104: =J92 -> 0.11988085 | K104: =K92/$N$78-1 -> 7.4704451 | L104: =L92/$N$78-1 -> 8.3236449 | M104: =M92/$N$78-1 -> 9.2667679 | N104: =N92/$N$78-1 -> 10.314821 | O104: =O92/$N$78-1 -> 11.486348
O107: WACC = Weighted Average Cost of Capital.
O108: This table requires the workbook calculation to be set to automatic to update.

Sheet Growth Factors out of sample
B2: Growth variables
B4: EBITDA Variables | G4: Cash From WC
B5: Label | C5: Best | D5: Base | E5: Worst | G5: Label | H5: Best | I5: Base | J5: Worst
B6: Start | C6: 0.05 | D6: 0.15 | E6: 0.25 | G6: Start | H6: 0.35 | I6: 0.4 | J6: 0.45
B7: End | C7: 0.35 | D7: 0.15 | E7: -0.05 | G7: End | H7: 0.5 | I7: 0.4 | J7: 0.3
B8: Years | C8: 3 | D8: 3 | E8: 3 | G8: Years | H8: 3 | I8: 3 | J8: 3
B9: Increase | C9: =(C7-C6)/C8 -> 0.1 | D9: =(D7-D6)/D8 -> 0 | E9: =(E7-E6)/E8 -> -0.1 | G9: Increase | H9: =(H7-H6)/H8 -> 0.05 | I9: =(I7-I6)/I8 -> 0 | J9: =(J7-J6)/J8 -> -0.05
B15: % Growths for EBITDA
B16: Case and definition | I16: 2015 | J16: =I16+1 -> 2016 | K16: =J16+1 -> 2017 | L16: Term
I18: 1 | J18: =I18+1 -> 2 | K18: =J18+1 -> 3 | L18: =K18+1 -> 4
B19: Best | H19: =C6 -> 0.05 | I19: =H19+$C$9 -> 0.15 | J19: =I19+$C$9 -> 0.25 | K19: =J19+$C$9 -> 0.35 | L19: =K19 -> 0.35
I22: 1 | J22: =I22+1 -> 2 | K22: =J22+1 -> 3 | L22: =K22+1 -> 4
B23: Base | H23: =D6 -> 0.15 | I23: =H23+$D$9 -> 0.15 | J23: =I23+$D$9 -> 0.15 | K23: =J23+$D$9 -> 0.15 | L23: =K23 -> 0.15
I26: 1 | J26: =I26+1 -> 2 | K26: =J26+1 -> 3 | L26: =K26+1 -> 4
B27: Worst | H27: =E6 -> 0.25 | I27: =H27+$E$9 -> 0.15 | J27: =I27+$E$9 -> 0.05 | K27: =J27+$E$9 -> -0.05 | L27: =K27 -> -0.05
B29: % Growths for Cash from WC
B30: Case and definition | I30: 2015 | J30: =I30+1 -> 2016 | K30: =J30+1 -> 2017 | L30: Term
I32: 1 | J32: =I32+1 -> 2 | K32: =J32+1 -> 3 | L32: =K32+1 -> 4
B33: Best | H33: =H6 -> 0.35 | I33: =H33+$H$9 -> 0.4 | J33: =I33+$H$9 -> 0.45 | K33: =J33+$H$9 -> 0.5 | L33: =K33 -> 0.5
I36: 1 | J36: =I36+1 -> 2 | K36: =J36+1 -> 3 | L36: =K36+1 -> 4
B37: Base | I37: =I6 -> 0.4 | J37: =I37 -> 0.4 | K37: =J37 -> 0.4 | L37: =K37 -> 0.4
I40: 1 | J40: =I40+1 -> 2 | K40: =J40+1 -> 3 | L40: =K40+1 -> 4
B41: Worst | H41: =J6 -> 0.45 | I41: =H41+$J$9 -> 0.4 | J41: =I41+$J$9 -> 0.35 | K41: =J41+$J$9 -> 0.3 | L41: =K41 -> 0.3

Sheet Inputs out of sample
B1: #VALUE!
B2: Drivers
B3: All figures in USD Millions unless stated
B4: Driver Switch | C4: 3 | I4: 2015 | J4: =I4+1 -> 2016 | K4: =J4+1 -> 2017 | L4: Term
B6: EBITDA Growth | I6: {=INDEX(I8:I10,$C$4)} -> 0.15 | J6: {=INDEX(J8:J10,$C$4)} -> 0.05 | K6: {=INDEX(K8:K10,$C$4)} -> -0.05 | L6: {=INDEX(L8:L10,$C$4)} -> -0.05
B8: Best | I8: ='Growth Factors out of sample'!I19 -> 0.15 | J8: ='Growth Factors out of sample'!J19 -> 0.25 | K8: ='Growth Factors out of sample'!K19 -> 0.35 | L8: ='Growth Factors out of sample'!L19 -> 0.35
B9: Base | I9: ='Growth Factors out of sample'!I23 -> 0.15 | J9: ='Growth Factors out of sample'!J23 -> 0.15 | K9: ='Growth Factors out of sample'!K23 -> 0.15 | L9: ='Growth Factors out of sample'!L23 -> 0.15
B10: Worst | I10: ='Growth Factors out of sample'!I27 -> 0.15 | J10: ='Growth Factors out of sample'!J27 -> 0.05 | K10: ='Growth Factors out of sample'!K27 -> -0.05 | L10: ='Growth Factors out of sample'!L27 -> -0.05
B12: Tax Depreciation | I12: {=INDEX(I14:I16,$C$4)} -> 150 | J12: {=INDEX(J14:J16,$C$4)} -> 150 | K12: {=INDEX(K14:K16,$C$4)} -> 150 | L12: {=INDEX(L14:L16,$C$4)} -> 150
B14: Best | I14: 250 | J14: 250 | K14: 250 | L14: 250
B15: Base | I15: =I14-50 -> 200 | J15: =J14-50 -> 200 | K15: =K14-50 -> 200 | L15: =L14-50 -> 200
B16: Worst | I16: =I15-50 -> 150 | J16: =J15-50 -> 150 | K16: =K15-50 -> 150 | L16: =L15-50 -> 150
B18: Cash from Working Capital | I18: {=INDEX(I20:I22,$C$4)} -> 140 | J18: {=INDEX(J20:J22,$C$4)} -> 189 | K18: {=INDEX(K20:K22,$C$4)} -> 245.7 | L18: {=INDEX(L20:L22,$C$4)} -> 245.7
B20: Best | H20: 200 | I20: =H20*('Growth Factors out of sample'!I33+1) -> 280 | J20: =I20*('Growth Factors out of sample'!J33+1) -> 406 | K20: =J20*('Growth Factors out of sample'!K33+1) -> 609 | L20: =K20 -> 609
B21: Base | H21: 150 | I21: =H21*('Growth Factors out of sample'!I37+1) -> 210 | J21: =I21*('Growth Factors out of sample'!J37+1) -> 294 | K21: =J21*('Growth Factors out of sample'!K37+1) -> 411.6 | L21: =K21 -> 411.6
B22: Worst | H22: 100 | I22: =H22*('Growth Factors out of sample'!I41+1) -> 140 | J22: =I22*('Growth Factors out of sample'!J41+1) -> 189 | K22: =J22*('Growth Factors out of sample'!K41+1) -> 245.7 | L22: =K22 -> 245.7

Sheet Compact DCF out of sample
B1: =Inputs!B1 -> #VALUE!
B2: Unlevered Free Cash Flow Schedule
B4: All figures in USD Millions unless stated | K4: 2013 | L4: =K4+1 -> 2014 | M4: =L4+1 -> 2015 | N4: =M4+1 -> 2016 | O4: =N4+1 -> 2017 | P4: Term
C7: PROFIT METRICS
C9: EBITDA Growth | L9: =L10/K10-1 -> -0.15331808 | M9: ='Inputs out of sample'!I6 -> 0.15 | N9: ='Inputs out of sample'!J6 -> 0.05 | O9: ='Inputs out of sample'!K6 -> -0.05 | P9: =O9 -> -0.05
C10: EBITDA | K10: 874 | L10: 740 | M10: =L10*(1+M9) -> 851 | N10: =M10*(1+N9) -> 893.55 | O10: =N10*(1+O9) -> 848.8725 | P10: =O10 -> 848.8725
C12: Tax Depreciation | K12: =K10-K13 -> 226 | L12: =L10-L13 -> 244 | M12: ='Inputs out of sample'!I12 -> 150 | N12: ='Inputs out of sample'!J12 -> 150 | O12: ='Inputs out of sample'!K12 -> 150 | P12: =O12 -> 150
C13: Operating Profit | K13: 648 | L13: 496 | M13: =M10-M12 -> 701 | N13: =N10-N12 -> 743.55 | O13: =O10-O12 -> 698.8725 | P13: =O13 -> 698.8725
C15: Tax Rate | K15: 0.104 | L15: 0.04 | M15: 0.147 | N15: 0.172 | O15: 0.238 | P15: =O15 -> 0.238
C16: Current Tax | K16: =K13*K15 -> 67.392 | L16: =L13*L15 -> 19.84 | M16: =M13*M15 -> 103.047 | N16: =N13*N15 -> 127.8906 | O16: =O13*O15 -> 166.33166 | P16: =P13*P15 -> 166.33166
C21: UNLEVERED FREE CASH FLOW
C23: EBITDA | M23: =M10 -> 851 | N23: =N10 -> 893.55 | O23: =O10 -> 848.8725 | P23: =P10 -> 848.8725
C24: Current Taxes | M24: =M16 -> 103.047 | N24: =N16 -> 127.8906 | O24: =O16 -> 166.33166 | P24: =P16 -> 166.33166
C25: Capital Expenditure 1 | M25: =-M12 -> -150 | N25: =-N12 -> -150 | O25: =-O12 -> -150 | P25: =-P12 -> -150
C26: Cash from Working Capital | M26: =-'Inputs out of sample'!I18 -> -140 | N26: =-'Inputs out of sample'!J18 -> -189 | O26: =-'Inputs out of sample'!K18 -> -245.7 | P26: =O26 -> -245.7
C27: Unlevered Free Cash Flow | M27: =SUM(M23:M26) -> 664.047 | N27: =SUM(N23:N26) -> 682.4406 | O27: =SUM(O23:O26) -> 619.50416 | P27: =SUM(P23:P26) -> 619.50416
P31: Capital expenditure has been set equal to tax depreciation.
B35: Discounted Cash Flow Schedule
B37: All figures in USD thousands unless stated | L37: Valuation | M37: Discrete Forecast | P37: Term
L38: (YY-MM-DD) | M38: (YY-MM-DD) | N38: (YY-MM-DD) | O38: (YY-MM-DD) | P38: (YY-MM-DD)
L39: =DATE(G47,1,1) -> 41275 | M39: =DATE(G47,12,31) -> 41639 | N39: =EDATE(M39,12) -> 42004 | O39: =EDATE(N39,12) -> 42369 | P39: =EDATE(O39,12) -> 42735
M42: UNLEVERED FREE CASH FLOW
M43: =M27 -> 664.047 | N43: =N27 -> 682.4406 | O43: =O27 -> 619.50416 | P43: =P27 -> 619.50416
D46: ASSUMPTIONS | M46: CASH FLOW PROFILES
D47: First Year of Forecast | G47: 2013 | K47: Discrete Forecast | M47: =M43 -> 664.047 | N47: =N43 -> 682.4406 | O47: =O43 -> 619.50416
D48: Terminal Growth Rate | G48: 0.02 | K48: Terminal Value 2 | M48: 0 | N48: 0 | O48: =P43/(G49-G48) -> 8045.5085
D49: WACC 1 | G49: 0.097 | K49: Total Cash Flow | M49: =SUM(M47:M48) -> 664.047 | N49: =SUM(N47:N48) -> 682.4406 | O49: =SUM(O47:O48) -> 8665.0127
D54: ENTERPRISE VALUE | K54: EQUITY VALUE PER SHARE
D55: PV of Discrete | F55: =NPV(G49,M47:O47) -> 1641.6912 | G55: =F55/F57 -> 0.21221095 | K55: Equity Value | N55: =G64 -> 3636.1285
D56: PV of Terminal | F56: =NPV(G49,M48:O48) -> 6094.4373 | G56: =F56/F57 -> 0.78778905 | K56: Shares Outstanding | M56: (FD 000) | N56: 631
D57: Enterprise Value | F57: =SUM(F55:F56) -> 7736.1285 | G57: =SUM(G55:G56) -> 1 | K57: Equity Value | M57: (USD/sh) | N57: =N55/N56 -> 5.7624857
D61: EQUITY VALUE | K61: PREMIUM (DISCOUNT)
D62: Enterprise Value | G62: =F57 -> 7736.1285 | K62: Equity Value 3 | M62: (USD/sh) | N62: =N57 -> 5.7624857 | O62: 'The actual equity value for the year of 2018 had a High of $7.32/share
D63: Less: Net Debt | G63: -4100 | K63: Current Price | M63: (USD/sh) | N63: 0.4 | O63: This was the share price in 2013
D64: Equity Value | G64: =SUM(G62:G63) -> 3636.1285 | K64: Premium (Discount) | N64: =N62/N63-1 -> 13.406214
N68: WACC = Weighted Average Cost of Capital.
N69: The growing perpetuity method was used to calculate the terminal value.
B73: Sensitivity Analysis
B75: All figures in USD thousands unless stated
D78: Terminal Growth Rate | G78: =G48 -> 0.02 | K78: Shares Outstanding | M78: (FD 000) | N78: =N56 -> 631
D79: WACC 1 | G79: =G49 -> 0.097 | K79: Current Price | M79: ($/sh) | N79: =N63 -> 0.4
D80: Enterprise Value | G80: =F57 -> 7736.1285
D81: Net Debt | G81: =-G63 -> 4100
D85: ENTERPRISE VALUE 2 | K85: EQUITY VALUE PER SHARE
D87: Terminal Growth Rate | K87: Terminal Growth Rate
C88: =G80 -> 7736.1285 | D88: =E88-0.005 -> 0.015 | E88: =F88-0.005 -> 0.02 | F88: 0.025 | G88: =F88+0.005 -> 0.03 | H88: =G88+0.005 -> 0.035 | K88: {=D88:H88} -> 0.015 | L88: 0.02 | M88: 0.025 | N88: 0.03 | O88: 0.035
B89: WACC | C89: =C90-0.01 -> 0.079880848 | D89: 9274.3697 | E89: 9907.4842 | F89: 10655.96 | G89: 11554.489 | H89: 12653.221 | I89: WACC | J89: =C89 -> 0.079880848 | K89: =D101/$N$78 -> 8.200269 | L89: =E101/$N$78 -> 9.20362 | M89: =F101/$N$78 -> 10.389794 | N89: =G101/$N$78 -> 11.813771 | O89: =H101/$N$78 -> 13.555026
C90: =C91-0.01 -> 0.089880848 | D90: 8052.857 | E90: 8510.1013 | F90: 9037.82 | G90: 9653.6668 | H90: 10381.729 | J90: =C90 -> 0.089880848 | K90: =D102/$N$78 -> 6.2644327 | L90: =E102/$N$78 -> 6.989067 | M90: =F102/$N$78 -> 7.8253882 | N90: =G102/$N$78 -> 8.8013737 | O90: =H102/$N$78 -> 9.9551963
C91: 0.099880848 | D91: 7118.7258 | E91: 7462.0662 | F91: 7851.2582 | G91: 8296.1439 | H91: 8809.5991 | J91: =C91 -> 0.099880848 | K91: =D103/$N$78 -> 4.7840346 | L91: =E103/$N$78 -> 5.3281557 | M91: =F103/$N$78 -> 5.9449417 | N91: =G103/$N$78 -> 6.6499903 | O91: =H103/$N$78 -> 7.463707
C92: =C91+0.01 -> 0.10988085 | D92: 6381.1249 | E92: 6646.793 | F92: 6943.7601 | G92: 7277.9034 | H92: 7656.67 | J92: =C92 -> 0.10988085 | K92: =D104/$N$78 -> 3.6150949 | L92: =E104/$N$78 -> 4.036122 | M92: =F104/$N$78 -> 4.5067513 | N92: =G104/$N$78 -> 5.036297 | O92: =H104/$N$78 -> 5.6365611
C93: =C92+0.01 -> 0.11988085 | D93: 5783.8517 | E93: 5994.3848 | F93: 6227.1071 | G93: 6485.7217 | H93: 6774.8043 | J93: =C93 -> 0.11988085 | K93: =D105/$N$78 -> 2.6685447 | L93: =E105/$N$78 -> 3.0021946 | M93: =F105/$N$78 -> 3.3710096 | N93: =G105/$N$78 -> 3.7808585 | O93: =H105/$N$78 -> 4.2389925
D97: EQUITY VALUE | K97: PREMIUM (DISCOUNT) TO CURRENT PRICE
D99: Terminal Growth Rate | K99: Terminal Growth Rate
D100: =D88 -> 0.015 | E100: =E88 -> 0.02 | F100: =F88 -> 0.025 | G100: =G88 -> 0.03 | H100: =H88 -> 0.035 | K100: =K88 -> 0.015 | L100: =L88 -> 0.02 | M100: =M88 -> 0.025 | N100: =N88 -> 0.03 | O100: =O88 -> 0.035
B101: WACC | C101: =C89 -> 0.079880848 | D101: =D89-$G$81 -> 5174.3697 | E101: =E89-$G$81 -> 5807.4842 | F101: =F89-$G$81 -> 6555.9603 | G101: =G89-$G$81 -> 7454.4892 | H101: =H89-$G$81 -> 8553.2214 | I101: WACC | J101: =J89 -> 0.079880848 | K101: =K89/$N$79-1 -> 19.500672 | L101: =L89/$N$79-1 -> 22.00905 | M101: =M89/$N$79-1 -> 24.974486 | N101: =N89/$N$79-1 -> 28.534426 | O101: =O89/$N$79-1 -> 32.887565
C102: =C90 -> 0.089880848 | D102: =D90-$G$81 -> 3952.857 | E102: =E90-$G$81 -> 4410.1013 | F102: =F90-$G$81 -> 4937.82 | G102: =G90-$G$81 -> 5553.6668 | H102: =H90-$G$81 -> 6281.7288 | J102: =J90 -> 0.089880848 | K102: =K90/$N$79-1 -> 14.661082 | L102: =L90/$N$79-1 -> 16.472667 | M102: =M90/$N$79-1 -> 18.563471 | N102: =N90/$N$79-1 -> 21.003434 | O102: =O90/$N$79-1 -> 23.887991
C103: =C91 -> 0.099880848 | D103: =D91-$G$81 -> 3018.7258 | E103: =E91-$G$81 -> 3362.0662 | F103: =F91-$G$81 -> 3751.2582 | G103: =G91-$G$81 -> 4196.1439 | H103: =H91-$G$81 -> 4709.5991 | J103: =J91 -> 0.099880848 | K103: =K91/$N$79-1 -> 10.960087 | L103: =L91/$N$79-1 -> 12.320389 | M103: =M91/$N$79-1 -> 13.862354 | N103: =N91/$N$79-1 -> 15.624976 | O103: =O91/$N$79-1 -> 17.659268
C104: =C92 -> 0.10988085 | D104: =D92-$G$81 -> 2281.1249 | E104: =E92-$G$81 -> 2546.793 | F104: =F92-$G$81 -> 2843.7601 | G104: =G92-$G$81 -> 3177.9034 | H104: =H92-$G$81 -> 3556.67 | J104: =J92 -> 0.10988085 | K104: =K92/$N$79-1 -> 8.0377373 | L104: =L92/$N$79-1 -> 9.0903051 | M104: =M92/$N$79-1 -> 10.266878 | N104: =N92/$N$79-1 -> 11.590742 | O104: =O92/$N$79-1 -> 13.091403
C105: =C93 -> 0.11988085 | D105: =D93-$G$81 -> 1683.8517 | E105: =E93-$G$81 -> 1894.3848 | F105: =F93-$G$81 -> 2127.1071 | G105: =G93-$G$81 -> 2385.7217 | H105: =H93-$G$81 -> 2674.8043 | J105: =J93 -> 0.11988085 | K105: =K93/$N$79-1 -> 5.6713617 | L105: =L93/$N$79-1 -> 6.5054865 | M105: =M93/$N$79-1 -> 7.4275241 | N105: =N93/$N$79-1 -> 8.4521462 | O105: =O93/$N$79-1 -> 9.5974812
O108: WACC = Weighted Average Cost of Capital.
O109: This table requires the workbook calculation to be set to automatic to update.
